Workbook

Sheet Assumptions
A1: LIQUIDITY MODEL · ASSUMPTIONS
A2: Blue-bordered cells are editable inputs · All calculations update automatically
A3: REVENUE DRIVERS
A4: Parameter | B4: Value | C4: Notes
A5: Conversion Rate | B5: 0.05 | C5: Lead-to-sale conversion %
A6: Average Check ($) | B6: 2500 | C6: Average revenue per new sale
A7: Monthly Lead Count | B7: 100 | C7: Leads entering pipeline per month
A8: Lead Growth MoM (%) | B8: 0.05 | C8: Monthly growth in lead count
A9: Opening MRR ($) | B9: 120000 | C9: Existing MRR at model start
A10: Base Churn Rate (%) | B10: 0.03 | C10: Monthly logo churn on existing MRR
A12: COST DRIVERS
A13: Parameter | B13: Value | C13: Notes
A14: Rent ($) | B14: 8000 | C14: Fixed monthly office rent
A15: Software / SaaS ($) | B15: 5000 | C15: Fixed SaaS licences
A16: Payroll ($) | B16: 65000 | C16: Base monthly payroll (ФОТ)
A17: Infrastructure ($) | B17: 10000 | C17: Cloud / hosting
A18: Support ($) | B18: 7000 | C18: Customer support team
A19: Marketing Base ($) | B19: 13000 | C19: Campaigns & ads base spend
A20: Variable Costs (% Rev) | B20: 0.03 | C20: Variable costs as % of revenue
A21: Payroll Annual Growth (%) | B21: 0.1 | C21: Annual payroll growth (new hires). Set 0 or use Freeze Hiring to stop.
A22: MACRO
A23: Parameter | B23: Value | C23: Notes
A24: Inflation (%) | B24: 0.03 | C24: Annual inflation applied to fixed costs
A25: Tax Rate (%) | B25: 0.2 | C25: Effective corporate tax rate
A27: WORKING CAPITAL
A28: Parameter | B28: Value | C28: Notes
A29: AR Delay (days) | B29: 30 | C29: Days client payment is delayed (30=1mo lag)
A30: Inventory Turnover | B30: 6 | C30: Not connected. For product cos: add Inventory=COGS/Inv_Turnover as Outflow row.
A31: Support Scale Rate (% Rev) | B31: 0.05 | C31: Support = MAX(Base, Gross_Revenue × this rate). Uses MRR/Gross Revenue (row 12), not cash inflow. Scales with business size.
A32: CRISIS EVENT TRIGGERS
A33: Parameter | B33: Value | C33: Notes
A34: Opening Cash ($) | B34: 500000 | C34: Starting cash balance
A35: Crisis Churn Month | B35: 7 | C35: Crisis churn applies FROM this month (inclusive). Formula: IF(month>=B35, crisis_rate, base_rate).
A36: Crisis Churn Rate (%) | B36: 0.12 | C36: Churn rate used from Crisis_Churn_Month onwards (inclusive).
A37: Crisis Salary Month | B37: 9 | C37: Month salary cost hike begins
A38: Crisis Salary Mult | B38: 1.3 | C38: Salary multiplier after trigger
A39: Crisis Mktg Month | B39: 11 | C39: Month marketing hike begins
A40: Crisis Mktg Mult | B40: 1.4 | C40: Marketing spend multiplier after trigger
A41: Runway Alert (months) | B41: 3 | C41: Alert threshold for low runway

Sheet Decisions
A1: ANTI-CRISIS DECISIONS · CONTROL PANEL
A3: MEASURE | B3: EFFECT | C3: UNIT | D3: STATUS (1- yes) | E3: DESCRIPTION / IMPACT | F3: APPLY MONTH
A4: Cut Marketing Spend | B4: 0.5 | C4: % | D4: 1 | E4: Reduces marketing by 50% → pause paid ads | F4: —
A5: Cut Headcount (Layoffs) | B5: 0.2 | C5: % | D5: 0 | E5: Reduces payroll by 20% → freeze + reduction | F5: —
A6: Freeze Hiring | B6: 0 | C6: binary | D6: 1 | E6: Freeze hiring: payroll growth stops (growth rate in Assumptions B21 → 0). Base salaries still apply; no new headcount costs. | F6: —
A7: Raise Prices | B7: 0.1 | C7: % | D7: 0 | E7: Increases avg check by 10% | F7: —
A8: Reduce Churn (Retention) | B8: 0.02 | C8: % | D8: 0 | E8: Retention campaign drops churn by 2pp | F8: —
A9: Kill Infra 20% | B9: 0.2 | C9: % | D9: 0 | E9: Audit & cut unused cloud/SaaS by 20% | F9: —
A10: Collect AR Faster | B10: 15 | C10: days | D10: 0 | E10: Shorten AR delay by 15 days | F10: —
A11: Emergency Fundraise | B11: 200000 | C11: $ | D11: 0 | E11: One-time cash injection in model month. Apply Month must be integer 1–24; invalid values silently ignored. ⬅ Only this row uses 'Apply Month' column. | F11: 1
A14: ℹ️ Blue=editable. Status 1=ACTIVE, 0=OFF. Column F ('Apply Month') is ONLY for Emergency Fundraise (row 11). All other decisions apply from Month 1.

Sheet Cash Flow Model
A1: CASH FLOW & LIQUIDITY MODEL
A2: AVG BURN RATE | D2: MIN RUNWAY | G2: BREAKEVEN REVENUE | J2: OPENING CASH | M2: WORST MONTH NCF
A3: =IFERROR(AVERAGEIF(C28:Z28,">0"),0) -> 108080 | D3: =IFERROR(_xludf.aggregate(15,6,IF((C29:Z29>0)*(ISNUMBER(C29:Z29)),C29:Z29),1),"✅ Safe") -> ✅ Safe | G3: =IFERROR(AVERAGE(C31:Z31),0) -> 121118.43 | J3: =Assumptions!B34 -> 500000 | M3: =MIN(C25:Z25) -> -108080
A4: Monthly avg when cash-negative | D4: Months of runway remaining | G4: Revenue needed to cover costs | J4: Starting cash balance | M4: Single worst month cash flow
A6: ℹ Month 1 Inflow = $0 by design: AR Delay = 30 days means January cash arrives in February. Change AR Delay in Assumptions (B29) to 0 for immediate collection. Opening Cash covers the gap.
A7: METRIC | B7: TYPE | C7: JAN | D7: FEB | E7: MAR | F7: APR | G7: MAY | H7: JUN | I7: JUL | J7: AUG | K7: SEP | L7: OCT | M7: NOV | N7: DEC | O7: JAN+1 | P7: FEB+1 | Q7: MAR+1 | R7: APR+1 | S7: MAY+1 | T7: JUN+1 | U7: JUL+1 | V7: AUG+1 | W7: SEP+1 | X7: OCT+1 | Y7: NOV+1 | Z7: DEC+1 | AA7: FORMULA NOTES
A8: ▲ INFLOW
A9: Leads (Pipeline) | B9: Drivers | C9: =Assumptions!B7 -> 100 | D9: =ROUND(C9*(1+Assumptions!B8),0) -> 105 | E9: =ROUND(D9*(1+Assumptions!B8),0) -> 110 | F9: =ROUND(E9*(1+Assumptions!B8),0) -> 116 | G9: =ROUND(F9*(1+Assumptions!B8),0) -> 122 | H9: =ROUND(G9*(1+Assumptions!B8),0) -> 128 | I9: =ROUND(H9*(1+Assumptions!B8),0) -> 134 | J9: =ROUND(I9*(1+Assumptions!B8),0) -> 141 | K9: =ROUND(J9*(1+Assumptions!B8),0) -> 148 | L9: =ROUND(K9*(1+Assumptions!B8),0) -> 155 | M9: =ROUND(L9*(1+Assumptions!B8),0) -> 163 | N9: =ROUND(M9*(1+Assumptions!B8),0) -> 171 | O9: =ROUND(N9*(1+Assumptions!B8),0) -> 180 | P9: =ROUND(O9*(1+Assumptions!B8),0) -> 189 | Q9: =ROUND(P9*(1+Assumptions!B8),0) -> 198 | R9: =ROUND(Q9*(1+Assumptions!B8),0) -> 208 | S9: =ROUND(R9*(1+Assumptions!B8),0) -> 218 | T9: =ROUND(S9*(1+Assumptions!B8),0) -> 229 | U9: =ROUND(T9*(1+Assumptions!B8),0) -> 240 | V9: =ROUND(U9*(1+Assumptions!B8),0) -> 252 | W9: =ROUND(V9*(1+Assumptions!B8),0) -> 265 | X9: =ROUND(W9*(1+Assumptions!B8),0) -> 278 | Y9: =ROUND(X9*(1+Assumptions!B8),0) -> 292 | Z9: =ROUND(Y9*(1+Assumptions!B8),0) -> 307 | AA9: Month 1=Lead_Count(B7). Grows at Lead_Growth(B8) MoM.
A10: New MRR Added (→ MRR base) | B10: Driver | C10: =ROUND(C9*Assumptions!B5*Assumptions!B6*(1+Decisions!D7*Decisions!B7),0) -> 12500 | D10: =ROUND(D9*Assumptions!B5*Assumptions!B6*(1+Decisions!D7*Decisions!B7),0) -> 13125 | E10: =ROUND(E9*Assumptions!B5*Assumptions!B6*(1+Decisions!D7*Decisions!B7),0) -> 13750 | F10: =ROUND(F9*Assumptions!B5*Assumptions!B6*(1+Decisions!D7*Decisions!B7),0) -> 14500 | G10: =ROUND(G9*Assumptions!B5*Assumptions!B6*(1+Decisions!D7*Decisions!B7),0) -> 15250 | H10: =ROUND(H9*Assumptions!B5*Assumptions!B6*(1+Decisions!D7*Decisions!B7),0) -> 16000 | I10: =ROUND(I9*Assumptions!B5*Assumptions!B6*(1+Decisions!D7*Decisions!B7),0) -> 16750 | J10: =ROUND(J9*Assumptions!B5*Assumptions!B6*(1+Decisions!D7*Decisions!B7),0) -> 17625 | K10: =ROUND(K9*Assumptions!B5*Assumptions!B6*(1+Decisions!D7*Decisions!B7),0) -> 18500 | L10: =ROUND(L9*Assumptions!B5*Assumptions!B6*(1+Decisions!D7*Decisions!B7),0) -> 19375 | M10: =ROUND(M9*Assumptions!B5*Assumptions!B6*(1+Decisions!D7*Decisions!B7),0) -> 20375 | N10: =ROUND(N9*Assumptions!B5*Assumptions!B6*(1+Decisions!D7*Decisions!B7),0) -> 21375 | O10: =ROUND(O9*Assumptions!B5*Assumptions!B6*(1+Decisions!D7*Decisions!B7),0) -> 22500 | P10: =ROUND(P9*Assumptions!B5*Assumptions!B6*(1+Decisions!D7*Decisions!B7),0) -> 23625 | Q10: =ROUND(Q9*Assumptions!B5*Assumptions!B6*(1+Decisions!D7*Decisions!B7),0) -> 24750 | R10: =ROUND(R9*Assumptions!B5*Assumptions!B6*(1+Decisions!D7*Decisions!B7),0) -> 26000 | S10: =ROUND(S9*Assumptions!B5*Assumptions!B6*(1+Decisions!D7*Decisions!B7),0) -> 27250 | T10: =ROUND(T9*Assumptions!B5*Assumptions!B6*(1+Decisions!D7*Decisions!B7),0) -> 28625 | U10: =ROUND(U9*Assumptions!B5*Assumptions!B6*(1+Decisions!D7*Decisions!B7),0) -> 30000 | V10: =ROUND(V9*Assumptions!B5*Assumptions!B6*(1+Decisions!D7*Decisions!B7),0) -> 31500 | W10: =ROUND(W9*Assumptions!B5*Assumptions!B6*(1+Decisions!D7*Decisions!B7),0) -> 33125 | X10: =ROUND(X9*Assumptions!B5*Assumptions!B6*(1+Decisions!D7*Decisions!B7),0) -> 34750 | Y10: =ROUND(Y9*Assumptions!B5*Assumptions!B6*(1+Decisions!D7*Decisions!B7),0) -> 36500 | Z10: =ROUND(Z9*Assumptions!B5*Assumptions!B6*(1+Decisions!D7*Decisions!B7),0) -> 38375 | AA10: New recurring revenue won. Added to MRR base next month. NOT a separate cash inflow – eliminates double-count. Raise Prices: D7×B7.
A11: MRR (Existing Base) | B11: Revenue | C11: =Assumptions!B9 -> 120000 | D11: =ROUND((C11+C10)*(1-MAX(0,IF(2>=Assumptions!B35,Assumptions!B36,Assumptions!B10)-Decisions!D8*Decisions!B8)),0) -> 128525 | E11: =ROUND((D11+D10)*(1-MAX(0,IF(3>=Assumptions!B35,Assumptions!B36,Assumptions!B10)-Decisions!D8*Decisions!B8)),0) -> 137401 | F11: =ROUND((E11+E10)*(1-MAX(0,IF(4>=Assumptions!B35,Assumptions!B36,Assumptions!B10)-Decisions!D8*Decisions!B8)),0) -> 146616 | G11: =ROUND((F11+F10)*(1-MAX(0,IF(5>=Assumptions!B35,Assumptions!B36,Assumptions!B10)-Decisions!D8*Decisions!B8)),0) -> 156283 | H11: =ROUND((G11+G10)*(1-MAX(0,IF(6>=Assumptions!B35,Assumptions!B36,Assumptions!B10)-Decisions!D8*Decisions!B8)),0) -> 166387 | I11: =ROUND((H11+H10)*(1-MAX(0,IF(7>=Assumptions!B35,Assumptions!B36,Assumptions!B10)-Decisions!D8*Decisions!B8)),0) -> 160501 | J11: =ROUND((I11+I10)*(1-MAX(0,IF(8>=Assumptions!B35,Assumptions!B36,Assumptions!B10)-Decisions!D8*Decisions!B8)),0) -> 155981 | K11: =ROUND((J11+J10)*(1-MAX(0,IF(9>=Assumptions!B35,Assumptions!B36,Assumptions!B10)-Decisions!D8*Decisions!B8)),0) -> 152773 | L11: =ROUND((K11+K10)*(1-MAX(0,IF(10>=Assumptions!B35,Assumptions!B36,Assumptions!B10)-Decisions!D8*Decisions!B8)),0) -> 150720 | M11: =ROUND((L11+L10)*(1-MAX(0,IF(11>=Assumptions!B35,Assumptions!B36,Assumptions!B10)-Decisions!D8*Decisions!B8)),0) -> 149684 | N11: =ROUND((M11+M10)*(1-MAX(0,IF(12>=Assumptions!B35,Assumptions!B36,Assumptions!B10)-Decisions!D8*Decisions!B8)),0) -> 149652 | O11: =ROUND((N11+N10)*(1-MAX(0,IF(13>=Assumptions!B35,Assumptions!B36,Assumptions!B10)-Decisions!D8*Decisions!B8)),0) -> 150504 | P11: =ROUND((O11+O10)*(1-MAX(0,IF(14>=Assumptions!B35,Assumptions!B36,Assumptions!B10)-Decisions!D8*Decisions!B8)),0) -> 152244 | Q11: =ROUND((P11+P10)*(1-MAX(0,IF(15>=Assumptions!B35,Assumptions!B36,Assumptions!B10)-Decisions!D8*Decisions!B8)),0) -> 154765 | R11: =ROUND((Q11+Q10)*(1-MAX(0,IF(16>=Assumptions!B35,Assumptions!B36,Assumptions!B10)-Decisions!D8*Decisions!B8)),0) -> 157973 | S11: =ROUND((R11+R10)*(1-MAX(0,IF(17>=Assumptions!B35,Assumptions!B36,Assumptions!B10)-Decisions!D8*Decisions!B8)),0) -> 161896 | T11: =ROUND((S11+S10)*(1-MAX(0,IF(18>=Assumptions!B35,Assumptions!B36,Assumptions!B10)-Decisions!D8*Decisions!B8)),0) -> 166448 | U11: =ROUND((T11+T10)*(1-MAX(0,IF(19>=Assumptions!B35,Assumptions!B36,Assumptions!B10)-Decisions!D8*Decisions!B8)),0) -> 171664 | V11: =ROUND((U11+U10)*(1-MAX(0,IF(20>=Assumptions!B35,Assumptions!B36,Assumptions!B10)-Decisions!D8*Decisions!B8)),0) -> 177464 | W11: =ROUND((V11+V10)*(1-MAX(0,IF(21>=Assumptions!B35,Assumptions!B36,Assumptions!B10)-Decisions!D8*Decisions!B8)),0) -> 183888 | X11: =ROUND((W11+W10)*(1-MAX(0,IF(22>=Assumptions!B35,Assumptions!B36,Assumptions!B10)-Decisions!D8*Decisions!B8)),0) -> 190971 | Y11: =ROUND((X11+X10)*(1-MAX(0,IF(23>=Assumptions!B35,Assumptions!B36,Assumptions!B10)-Decisions!D8*Decisions!B8)),0) -> 198634 | Z11: =ROUND((Y11+Y10)*(1-MAX(0,IF(24>=Assumptions!B35,Assumptions!B36,Assumptions!B10)-Decisions!D8*Decisions!B8)),0) -> 206918 | AA11: SaaS: (Prior MRR + New MRR Won) × (1−churn). Reduce Churn decision D8×B8. Crisis churn B35/B36.
A12: Gross Revenue (MRR) | B12: Revenue | C12: =C11 -> 120000 | D12: =D11 -> 128525 | E12: =E11 -> 137401 | F12: =F11 -> 146616 | G12: =G11 -> 156283 | H12: =H11 -> 166387 | I12: =I11 -> 160501 | J12: =J11 -> 155981 | ... Z12: =Z11 -> 206918 | AA12: MRR only. New Sales already in MRR base.
A13: Total Inflow (AR-lag adj) | B13: Revenue | C13: =ROUND(MIN(1,(MAX(0,Assumptions!B29-Decisions!D10*Decisions!B10))/30)*0+(1-MIN(1,(MAX(0,Assumptions!B29-Decisions!D10*Decisions!B10))/30))*C12,0) -> 0 | D13: =ROUND(MIN(1,(MAX(0,Assumptions!B29-Decisions!D10*Decisions!B10))/30)*C12+(1-MIN(1,(MAX(0,Assumptions!B29-Decisions!D10*Decisions!B10))/30))*D12,0) -> 120000 | E13: =ROUND(MIN(1,(MAX(0,Assumptions!B29-Decisions!D10*Decisions!B10))/30)*D12+(1-MIN(1,(MAX(0,Assumptions!B29-Decisions!D10*Decisions!B10))/30))*E12,0) -> 128525 | F13: =ROUND(MIN(1,(MAX(0,Assumptions!B29-Decisions!D10*Decisions!B10))/30)*E12+(1-MIN(1,(MAX(0,Assumptions!B29-Decisions!D10*Decisions!B10))/30))*F12,0) -> 137401 | G13: =ROUND(MIN(1,(MAX(0,Assumptions!B29-Decisions!D10*Decisions!B10))/30)*F12+(1-MIN(1,(MAX(0,Assumptions!B29-Decisions!D10*Decisions!B10))/30))*G12,0) -> 146616 | H13: =ROUND(MIN(1,(MAX(0,Assumptions!B29-Decisions!D10*Decisions!B10))/30)*G12+(1-MIN(1,(MAX(0,Assumptions!B29-Decisions!D10*Decisions!B10))/30))*H12,0) -> 156283 | I13: =ROUND(MIN(1,(MAX(0,Assumptions!B29-Decisions!D10*Decisions!B10))/30)*H12+(1-MIN(1,(MAX(0,Assumptions!B29-Decisions!D10*Decisions!B10))/30))*I12,0) -> 166387 | J13: =ROUND(MIN(1,(MAX(0,Assumptions!B29-Decisions!D10*Decisions!B10))/30)*I12+(1-MIN(1,(MAX(0,Assumptions!B29-Decisions!D10*Decisions!B10))/30))*J12,0) -> 160501 | K13: =ROUND(MIN(1,(MAX(0,Assumptions!B29-Decisions!D10*Decisions!B10))/30)*J12+(1-MIN(1,(MAX(0,Assumptions!B29-Decisions!D10*Decisions!B10))/30))*K12,0) -> 155981 | L13: =ROUND(MIN(1,(MAX(0,Assumptions!B29-Decisions!D10*Decisions!B10))/30)*K12+(1-MIN(1,(MAX(0,Assumptions!B29-Decisions!D10*Decisions!B10))/30))*L12,0) -> 152773 | M13: =ROUND(MIN(1,(MAX(0,Assumptions!B29-Decisions!D10*Decisions!B10))/30)*L12+(1-MIN(1,(MAX(0,Assumptions!B29-Decisions!D10*Decisions!B10))/30))*M12,0) -> 150720 | N13: =ROUND(MIN(1,(MAX(0,Assumptions!B29-Decisions!D10*Decisions!B10))/30)*M12+(1-MIN(1,(MAX(0,Assumptions!B29-Decisions!D10*Decisions!B10))/30))*N12,0) -> 149684 | O13: =ROUND(MIN(1,(MAX(0,Assumptions!B29-Decisions!D10*Decisions!B10))/30)*N12+(1-MIN(1,(MAX(0,Assumptions!B29-Decisions!D10*Decisions!B10))/30))*O12,0) -> 149652 | P13: =ROUND(MIN(1,(MAX(0,Assumptions!B29-Decisions!D10*Decisions!B10))/30)*O12+(1-MIN(1,(MAX(0,Assumptions!B29-Decisions!D10*Decisions!B10))/30))*P12,0) -> 150504 | Q13: =ROUND(MIN(1,(MAX(0,Assumptions!B29-Decisions!D10*Decisions!B10))/30)*P12+(1-MIN(1,(MAX(0,Assumptions!B29-Decisions!D10*Decisions!B10))/30))*Q12,0) -> 152244 | R13: =ROUND(MIN(1,(MAX(0,Assumptions!B29-Decisions!D10*Decisions!B10))/30)*Q12+(1-MIN(1,(MAX(0,Assumptions!B29-Decisions!D10*Decisions!B10))/30))*R12,0) -> 154765 | S13: =ROUND(MIN(1,(MAX(0,Assumptions!B29-Decisions!D10*Decisions!B10))/30)*R12+(1-MIN(1,(MAX(0,Assumptions!B29-Decisions!D10*Decisions!B10))/30))*S12,0) -> 157973 | T13: =ROUND(MIN(1,(MAX(0,Assumptions!B29-Decisions!D10*Decisions!B10))/30)*S12+(1-MIN(1,(MAX(0,Assumptions!B29-Decisions!D10*Decisions!B10))/30))*T12,0) -> 161896 | U13: =ROUND(MIN(1,(MAX(0,Assumptions!B29-Decisions!D10*Decisions!B10))/30)*T12+(1-MIN(1,(MAX(0,Assumptions!B29-Decisions!D10*Decisions!B10))/30))*U12,0) -> 166448 | V13: =ROUND(MIN(1,(MAX(0,Assumptions!B29-Decisions!D10*Decisions!B10))/30)*U12+(1-MIN(1,(MAX(0,Assumptions!B29-Decisions!D10*Decisions!B10))/30))*V12,0) -> 171664 | W13: =ROUND(MIN(1,(MAX(0,Assumptions!B29-Decisions!D10*Decisions!B10))/30)*V12+(1-MIN(1,(MAX(0,Assumptions!B29-Decisions!D10*Decisions!B10))/30))*W12,0) -> 177464 | X13: =ROUND(MIN(1,(MAX(0,Assumptions!B29-Decisions!D10*Decisions!B10))/30)*W12+(1-MIN(1,(MAX(0,Assumptions!B29-Decisions!D10*Decisions!B10))/30))*X12,0) -> 183888 | Y13: =ROUND(MIN(1,(MAX(0,Assumptions!B29-Decisions!D10*Decisions!B10))/30)*X12+(1-MIN(1,(MAX(0,Assumptions!B29-Decisions!D10*Decisions!B10))/30))*Y12,0) -> 190971 | Z13: =ROUND(MIN(1,(MAX(0,Assumptions!B29-Decisions!D10*Decisions!B10))/30)*Y12+(1-MIN(1,(MAX(0,Assumptions!B29-Decisions!D10*Decisions!B10))/30))*Z12,0) -> 198634 | AA13: Proportional lag: frac=MIN(1,AR_days/30). Models 0–30d range precisely. ⚠ Known limitation: delays >30d (45/60/90d) all map to frac=1 (full 1-month shift). For multi-month waterfall, extend model. B29, D10/B10.
A14: ▼ OUTFLOW
A15: Payroll (ФОТ) | B15: Cost | C15: =ROUND(Assumptions!B16*(1+IF(Decisions!D6=1,0,Assumptions!B21/12))^(0)*IF(1>=Assumptions!B37,Assumptions!B38,1)*(1-Decisions!D5*Decisions!B5),0) -> 65000 | D15: =ROUND(Assumptions!B16*(1+IF(Decisions!D6=1,0,Assumptions!B21/12))^(1)*IF(2>=Assumptions!B37,Assumptions!B38,1)*(1-Decisions!D5*Decisions!B5),0) -> 65000 | E15: =ROUND(Assumptions!B16*(1+IF(Decisions!D6=1,0,Assumptions!B21/12))^(2)*IF(3>=Assumptions!B37,Assumptions!B38,1)*(1-Decisions!D5*Decisions!B5),0) -> 65000 | F15: =ROUND(Assumptions!B16*(1+IF(Decisions!D6=1,0,Assumptions!B21/12))^(3)*IF(4>=Assumptions!B37,Assumptions!B38,1)*(1-Decisions!D5*Decisions!B5),0) -> 65000 | G15: =ROUND(Assumptions!B16*(1+IF(Decisions!D6=1,0,Assumptions!B21/12))^(4)*IF(5>=Assumptions!B37,Assumptions!B38,1)*(1-Decisions!D5*Decisions!B5),0) -> 65000 | H15: =ROUND(Assumptions!B16*(1+IF(Decisions!D6=1,0,Assumptions!B21/12))^(5)*IF(6>=Assumptions!B37,Assumptions!B38,1)*(1-Decisions!D5*Decisions!B5),0) -> 65000 | I15: =ROUND(Assumptions!B16*(1+IF(Decisions!D6=1,0,Assumptions!B21/12))^(6)*IF(7>=Assumptions!B37,Assumptions!B38,1)*(1-Decisions!D5*Decisions!B5),0) -> 65000 | J15: =ROUND(Assumptions!B16*(1+IF(Decisions!D6=1,0,Assumptions!B21/12))^(7)*IF(8>=Assumptions!B37,Assumptions!B38,1)*(1-Decisions!D5*Decisions!B5),0) -> 65000 | K15: =ROUND(Assumptions!B16*(1+IF(Decisions!D6=1,0,Assumptions!B21/12))^(8)*IF(9>=Assumptions!B37,Assumptions!B38,1)*(1-Decisions!D5*Decisions!B5),0) -> 84500 | L15: =ROUND(Assumptions!B16*(1+IF(Decisions!D6=1,0,Assumptions!B21/12))^(9)*IF(10>=Assumptions!B37,Assumptions!B38,1)*(1-Decisions!D5*Decisions!B5),0) -> 84500 | M15: =ROUND(Assumptions!B16*(1+IF(Decisions!D6=1,0,Assumptions!B21/12))^(10)*IF(11>=Assumptions!B37,Assumptions!B38,1)*(1-Decisions!D5*Decisions!B5),0) -> 84500 | N15: =ROUND(Assumptions!B16*(1+IF(Decisions!D6=1,0,Assumptions!B21/12))^(11)*IF(12>=Assumptions!B37,Assumptions!B38,1)*(1-Decisions!D5*Decisions!B5),0) -> 84500 | O15: =ROUND(Assumptions!B16*(1+IF(Decisions!D6=1,0,Assumptions!B21/12))^(12)*IF(13>=Assumptions!B37,Assumptions!B38,1)*(1-Decisions!D5*Decisions!B5),0) -> 84500 | P15: =ROUND(Assumptions!B16*(1+IF(Decisions!D6=1,0,Assumptions!B21/12))^(13)*IF(14>=Assumptions!B37,Assumptions!B38,1)*(1-Decisions!D5*Decisions!B5),0) -> 84500 | Q15: =ROUND(Assumptions!B16*(1+IF(Decisions!D6=1,0,Assumptions!B21/12))^(14)*IF(15>=Assumptions!B37,Assumptions!B38,1)*(1-Decisions!D5*Decisions!B5),0) -> 84500 | R15: =ROUND(Assumptions!B16*(1+IF(Decisions!D6=1,0,Assumptions!B21/12))^(15)*IF(16>=Assumptions!B37,Assumptions!B38,1)*(1-Decisions!D5*Decisions!B5),0) -> 84500 | S15: =ROUND(Assumptions!B16*(1+IF(Decisions!D6=1,0,Assumptions!B21/12))^(16)*IF(17>=Assumptions!B37,Assumptions!B38,1)*(1-Decisions!D5*Decisions!B5),0) -> 84500 | T15: =ROUND(Assumptions!B16*(1+IF(Decisions!D6=1,0,Assumptions!B21/12))^(17)*IF(18>=Assumptions!B37,Assumptions!B38,1)*(1-Decisions!D5*Decisions!B5),0) -> 84500 | U15: =ROUND(Assumptions!B16*(1+IF(Decisions!D6=1,0,Assumptions!B21/12))^(18)*IF(19>=Assumptions!B37,Assumptions!B38,1)*(1-Decisions!D5*Decisions!B5),0) -> 84500 | V15: =ROUND(Assumptions!B16*(1+IF(Decisions!D6=1,0,Assumptions!B21/12))^(19)*IF(20>=Assumptions!B37,Assumptions!B38,1)*(1-Decisions!D5*Decisions!B5),0) -> 84500 | W15: =ROUND(Assumptions!B16*(1+IF(Decisions!D6=1,0,Assumptions!B21/12))^(20)*IF(21>=Assumptions!B37,Assumptions!B38,1)*(1-Decisions!D5*Decisions!B5),0) -> 84500 | X15: =ROUND(Assumptions!B16*(1+IF(Decisions!D6=1,0,Assumptions!B21/12))^(21)*IF(22>=Assumptions!B37,Assumptions!B38,1)*(1-Decisions!D5*Decisions!B5),0) -> 84500 | Y15: =ROUND(Assumptions!B16*(1+IF(Decisions!D6=1,0,Assumptions!B21/12))^(22)*IF(23>=Assumptions!B37,Assumptions!B38,1)*(1-Decisions!D5*Decisions!B5),0) -> 84500 | Z15: =ROUND(Assumptions!B16*(1+IF(Decisions!D6=1,0,Assumptions!B21/12))^(23)*IF(24>=Assumptions!B37,Assumptions!B38,1)*(1-Decisions!D5*Decisions!B5),0) -> 84500 | AA15: Grows at B21/12 monthly UNLESS Freeze Hiring D6=1. Crisis mult B37/B38. Cut Headcount D5×B5.
A16: Rent | B16: Cost | C16: =ROUND(Assumptions!B14*(1+Assumptions!B24/12)^(0),0) -> 8000 | D16: =ROUND(Assumptions!B14*(1+Assumptions!B24/12)^(1),0) -> 8020 | E16: =ROUND(Assumptions!B14*(1+Assumptions!B24/12)^(2),0) -> 8040 | F16: =ROUND(Assumptions!B14*(1+Assumptions!B24/12)^(3),0) -> 8060 | G16: =ROUND(Assumptions!B14*(1+Assumptions!B24/12)^(4),0) -> 8080 | H16: =ROUND(Assumptions!B14*(1+Assumptions!B24/12)^(5),0) -> 8101 | I16: =ROUND(Assumptions!B14*(1+Assumptions!B24/12)^(6),0) -> 8121 | J16: =ROUND(Assumptions!B14*(1+Assumptions!B24/12)^(7),0) -> 8141 | K16: =ROUND(Assumptions!B14*(1+Assumptions!B24/12)^(8),0) -> 8161 | L16: =ROUND(Assumptions!B14*(1+Assumptions!B24/12)^(9),0) -> 8182 | M16: =ROUND(Assumptions!B14*(1+Assumptions!B24/12)^(10),0) -> 8202 | N16: =ROUND(Assumptions!B14*(1+Assumptions!B24/12)^(11),0) -> 8223 | O16: =ROUND(Assumptions!B14*(1+Assumptions!B24/12)^(12),0) -> 8243 | P16: =ROUND(Assumptions!B14*(1+Assumptions!B24/12)^(13),0) -> 8264 | Q16: =ROUND(Assumptions!B14*(1+Assumptions!B24/12)^(14),0) -> 8285 | R16: =ROUND(Assumptions!B14*(1+Assumptions!B24/12)^(15),0) -> 8305 | S16: =ROUND(Assumptions!B14*(1+Assumptions!B24/12)^(16),0) -> 8326 | T16: =ROUND(Assumptions!B14*(1+Assumptions!B24/12)^(17),0) -> 8347 | U16: =ROUND(Assumptions!B14*(1+Assumptions!B24/12)^(18),0) -> 8368 | V16: =ROUND(Assumptions!B14*(1+Assumptions!B24/12)^(19),0) -> 8389 | W16: =ROUND(Assumptions!B14*(1+Assumptions!B24/12)^(20),0) -> 8410 | X16: =ROUND(Assumptions!B14*(1+Assumptions!B24/12)^(21),0) -> 8431 | Y16: =ROUND(Assumptions!B14*(1+Assumptions!B24/12)^(22),0) -> 8452 | Z16: =ROUND(Assumptions!B14*(1+Assumptions!B24/12)^(23),0) -> 8473 | AA16: Rent(B14) inflation-adjusted monthly. Ref B14, Inflation B24
A17: Software / SaaS | B17: Cost | C17: =ROUND(Assumptions!B15*(1+Assumptions!B24/12)^(0),0) -> 5000 | D17: =ROUND(Assumptions!B15*(1+Assumptions!B24/12)^(1),0) -> 5013 | E17: =ROUND(Assumptions!B15*(1+Assumptions!B24/12)^(2),0) -> 5025 | F17: =ROUND(Assumptions!B15*(1+Assumptions!B24/12)^(3),0) -> 5038 | G17: =ROUND(Assumptions!B15*(1+Assumptions!B24/12)^(4),0) -> 5050 | H17: =ROUND(Assumptions!B15*(1+Assumptions!B24/12)^(5),0) -> 5063 | I17: =ROUND(Assumptions!B15*(1+Assumptions!B24/12)^(6),0) -> 5075 | J17: =ROUND(Assumptions!B15*(1+Assumptions!B24/12)^(7),0) -> 5088 | K17: =ROUND(Assumptions!B15*(1+Assumptions!B24/12)^(8),0) -> 5101 | L17: =ROUND(Assumptions!B15*(1+Assumptions!B24/12)^(9),0) -> 5114 | M17: =ROUND(Assumptions!B15*(1+Assumptions!B24/12)^(10),0) -> 5126 | N17: =ROUND(Assumptions!B15*(1+Assumptions!B24/12)^(11),0) -> 5139 | O17: =ROUND(Assumptions!B15*(1+Assumptions!B24/12)^(12),0) -> 5152 | P17: =ROUND(Assumptions!B15*(1+Assumptions!B24/12)^(13),0) -> 5165 | Q17: =ROUND(Assumptions!B15*(1+Assumptions!B24/12)^(14),0) -> 5178 | R17: =ROUND(Assumptions!B15*(1+Assumptions!B24/12)^(15),0) -> 5191 | S17: =ROUND(Assumptions!B15*(1+Assumptions!B24/12)^(16),0) -> 5204 | T17: =ROUND(Assumptions!B15*(1+Assumptions!B24/12)^(17),0) -> 5217 | U17: =ROUND(Assumptions!B15*(1+Assumptions!B24/12)^(18),0) -> 5230 | V17: =ROUND(Assumptions!B15*(1+Assumptions!B24/12)^(19),0) -> 5243 | W17: =ROUND(Assumptions!B15*(1+Assumptions!B24/12)^(20),0) -> 5256 | X17: =ROUND(Assumptions!B15*(1+Assumptions!B24/12)^(21),0) -> 5269 | Y17: =ROUND(Assumptions!B15*(1+Assumptions!B24/12)^(22),0) -> 5282 | Z17: =ROUND(Assumptions!B15*(1+Assumptions!B24/12)^(23),0) -> 5296 | AA17: Software(B15) inflation-adjusted. Ref B15, Inflation B24
A18: Infrastructure | B18: Cost | C18: =ROUND(Assumptions!B17*(1-Decisions!D9*Decisions!B9),0) -> 10000 | D18: =ROUND(Assumptions!B17*(1-Decisions!D9*Decisions!B9),0) -> 10000 | E18: =ROUND(Assumptions!B17*(1-Decisions!D9*Decisions!B9),0) -> 10000 | F18: =ROUND(Assumptions!B17*(1-Decisions!D9*Decisions!B9),0) -> 10000 | G18: =ROUND(Assumptions!B17*(1-Decisions!D9*Decisions!B9),0) -> 10000 | H18: =ROUND(Assumptions!B17*(1-Decisions!D9*Decisions!B9),0) -> 10000 | I18: =ROUND(Assumptions!B17*(1-Decisions!D9*Decisions!B9),0) -> 10000 | J18: =ROUND(Assumptions!B17*(1-Decisions!D9*Decisions!B9),0) -> 10000 | K18: =ROUND(Assumptions!B17*(1-Decisions!D9*Decisions!B9),0) -> 10000 | L18: =ROUND(Assumptions!B17*(1-Decisions!D9*Decisions!B9),0) -> 10000 | M18: =ROUND(Assumptions!B17*(1-Decisions!D9*Decisions!B9),0) -> 10000 | N18: =ROUND(Assumptions!B17*(1-Decisions!D9*Decisions!B9),0) -> 10000 | O18: =ROUND(Assumptions!B17*(1-Decisions!D9*Decisions!B9),0) -> 10000 | P18: =ROUND(Assumptions!B17*(1-Decisions!D9*Decisions!B9),0) -> 10000 | Q18: =ROUND(Assumptions!B17*(1-Decisions!D9*Decisions!B9),0) -> 10000 | R18: =ROUND(Assumptions!B17*(1-Decisions!D9*Decisions!B9),0) -> 10000 | S18: =ROUND(Assumptions!B17*(1-Decisions!D9*Decisions!B9),0) -> 10000 | T18: =ROUND(Assumptions!B17*(1-Decisions!D9*Decisions!B9),0) -> 10000 | U18: =ROUND(Assumptions!B17*(1-Decisions!D9*Decisions!B9),0) -> 10000 | V18: =ROUND(Assumptions!B17*(1-Decisions!D9*Decisions!B9),0) -> 10000 | W18: =ROUND(Assumptions!B17*(1-Decisions!D9*Decisions!B9),0) -> 10000 | X18: =ROUND(Assumptions!B17*(1-Decisions!D9*Decisions!B9),0) -> 10000 | Y18: =ROUND(Assumptions!B17*(1-Decisions!D9*Decisions!B9),0) -> 10000 | Z18: =ROUND(Assumptions!B17*(1-Decisions!D9*Decisions!B9),0) -> 10000 | AA18: Infra(B17) × (1 − Kill_Infra_decision D9×B9). Ref B17, Decisions D9/B9
A19: Support | B19: Cost | C19: =MAX(Assumptions!B18,ROUND(C12*Assumptions!B31,0)) -> 7000 | D19: =MAX(Assumptions!B18,ROUND(D12*Assumptions!B31,0)) -> 7000 | E19: =MAX(Assumptions!B18,ROUND(E12*Assumptions!B31,0)) -> 7000 | F19: =MAX(Assumptions!B18,ROUND(F12*Assumptions!B31,0)) -> 7331 | G19: =MAX(Assumptions!B18,ROUND(G12*Assumptions!B31,0)) -> 7814 | H19: =MAX(Assumptions!B18,ROUND(H12*Assumptions!B31,0)) -> 8319 | I19: =MAX(Assumptions!B18,ROUND(I12*Assumptions!B31,0)) -> 8025 | J19: =MAX(Assumptions!B18,ROUND(J12*Assumptions!B31,0)) -> 7799 | K19: =MAX(Assumptions!B18,ROUND(K12*Assumptions!B31,0)) -> 7639 | L19: =MAX(Assumptions!B18,ROUND(L12*Assumptions!B31,0)) -> 7536 | M19: =MAX(Assumptions!B18,ROUND(M12*Assumptions!B31,0)) -> 7484 | N19: =MAX(Assumptions!B18,ROUND(N12*Assumptions!B31,0)) -> 7483 | O19: =MAX(Assumptions!B18,ROUND(O12*Assumptions!B31,0)) -> 7525 | P19: =MAX(Assumptions!B18,ROUND(P12*Assumptions!B31,0)) -> 7612 | Q19: =MAX(Assumptions!B18,ROUND(Q12*Assumptions!B31,0)) -> 7738 | R19: =MAX(Assumptions!B18,ROUND(R12*Assumptions!B31,0)) -> 7899 | S19: =MAX(Assumptions!B18,ROUND(S12*Assumptions!B31,0)) -> 8095 | T19: =MAX(Assumptions!B18,ROUND(T12*Assumptions!B31,0)) -> 8322 | U19: =MAX(Assumptions!B18,ROUND(U12*Assumptions!B31,0)) -> 8583 | V19: =MAX(Assumptions!B18,ROUND(V12*Assumptions!B31,0)) -> 8873 | W19: =MAX(Assumptions!B18,ROUND(W12*Assumptions!B31,0)) -> 9194 | X19: =MAX(Assumptions!B18,ROUND(X12*Assumptions!B31,0)) -> 9549 | Y19: =MAX(Assumptions!B18,ROUND(Y12*Assumptions!B31,0)) -> 9932 | Z19: =MAX(Assumptions!B18,ROUND(Z12*Assumptions!B31,0)) -> 10346 | AA19: MAX(Base_Support B18, Gross_Rev×Scale B31). Accrual. B18,B31.
A20: Marketing | B20: Cost | C20: =ROUND(Assumptions!B19*IF(1>=Assumptions!B39,Assumptions!B40,1)*(1-Decisions!D4*Decisions!B4),0) -> 6500 | D20: =ROUND(Assumptions!B19*IF(2>=Assumptions!B39,Assumptions!B40,1)*(1-Decisions!D4*Decisions!B4),0) -> 6500 | E20: =ROUND(Assumptions!B19*IF(3>=Assumptions!B39,Assumptions!B40,1)*(1-Decisions!D4*Decisions!B4),0) -> 6500 | F20: =ROUND(Assumptions!B19*IF(4>=Assumptions!B39,Assumptions!B40,1)*(1-Decisions!D4*Decisions!B4),0) -> 6500 | G20: =ROUND(Assumptions!B19*IF(5>=Assumptions!B39,Assumptions!B40,1)*(1-Decisions!D4*Decisions!B4),0) -> 6500 | H20: =ROUND(Assumptions!B19*IF(6>=Assumptions!B39,Assumptions!B40,1)*(1-Decisions!D4*Decisions!B4),0) -> 6500 | I20: =ROUND(Assumptions!B19*IF(7>=Assumptions!B39,Assumptions!B40,1)*(1-Decisions!D4*Decisions!B4),0) -> 6500 | J20: =ROUND(Assumptions!B19*IF(8>=Assumptions!B39,Assumptions!B40,1)*(1-Decisions!D4*Decisions!B4),0) -> 6500 | K20: =ROUND(Assumptions!B19*IF(9>=Assumptions!B39,Assumptions!B40,1)*(1-Decisions!D4*Decisions!B4),0) -> 6500 | L20: =ROUND(Assumptions!B19*IF(10>=Assumptions!B39,Assumptions!B40,1)*(1-Decisions!D4*Decisions!B4),0) -> 6500 | M20: =ROUND(Assumptions!B19*IF(11>=Assumptions!B39,Assumptions!B40,1)*(1-Decisions!D4*Decisions!B4),0) -> 9100 | N20: =ROUND(Assumptions!B19*IF(12>=Assumptions!B39,Assumptions!B40,1)*(1-Decisions!D4*Decisions!B4),0) -> 9100 | O20: =ROUND(Assumptions!B19*IF(13>=Assumptions!B39,Assumptions!B40,1)*(1-Decisions!D4*Decisions!B4),0) -> 9100 | P20: =ROUND(Assumptions!B19*IF(14>=Assumptions!B39,Assumptions!B40,1)*(1-Decisions!D4*Decisions!B4),0) -> 9100 | Q20: =ROUND(Assumptions!B19*IF(15>=Assumptions!B39,Assumptions!B40,1)*(1-Decisions!D4*Decisions!B4),0) -> 9100 | R20: =ROUND(Assumptions!B19*IF(16>=Assumptions!B39,Assumptions!B40,1)*(1-Decisions!D4*Decisions!B4),0) -> 9100 | S20: =ROUND(Assumptions!B19*IF(17>=Assumptions!B39,Assumptions!B40,1)*(1-Decisions!D4*Decisions!B4),0) -> 9100 | T20: =ROUND(Assumptions!B19*IF(18>=Assumptions!B39,Assumptions!B40,1)*(1-Decisions!D4*Decisions!B4),0) -> 9100 | U20: =ROUND(Assumptions!B19*IF(19>=Assumptions!B39,Assumptions!B40,1)*(1-Decisions!D4*Decisions!B4),0) -> 9100 | V20: =ROUND(Assumptions!B19*IF(20>=Assumptions!B39,Assumptions!B40,1)*(1-Decisions!D4*Decisions!B4),0) -> 9100 | W20: =ROUND(Assumptions!B19*IF(21>=Assumptions!B39,Assumptions!B40,1)*(1-Decisions!D4*Decisions!B4),0) -> 9100 | X20: =ROUND(Assumptions!B19*IF(22>=Assumptions!B39,Assumptions!B40,1)*(1-Decisions!D4*Decisions!B4),0) -> 9100 | Y20: =ROUND(Assumptions!B19*IF(23>=Assumptions!B39,Assumptions!B40,1)*(1-Decisions!D4*Decisions!B4),0) -> 9100 | Z20: =ROUND(Assumptions!B19*IF(24>=Assumptions!B39,Assumptions!B40,1)*(1-Decisions!D4*Decisions!B4),0) -> 9100 | AA20: Mktg(B19) × crisis_mult(B39/B40) × (1 − Cut_Mktg D4×B4). Ref B19,B39,B40,D4,B4
A21: Variable Costs | B21: Cost | C21: =ROUND(C12*Assumptions!B20,0) -> 3600 | D21: =ROUND(D12*Assumptions!B20,0) -> 3856 | E21: =ROUND(E12*Assumptions!B20,0) -> 4122 | F21: =ROUND(F12*Assumptions!B20,0) -> 4398 | G21: =ROUND(G12*Assumptions!B20,0) -> 4688 | H21: =ROUND(H12*Assumptions!B20,0) -> 4992 | I21: =ROUND(I12*Assumptions!B20,0) -> 4815 | J21: =ROUND(J12*Assumptions!B20,0) -> 4679 | K21: =ROUND(K12*Assumptions!B20,0) -> 4583 | L21: =ROUND(L12*Assumptions!B20,0) -> 4522 | M21: =ROUND(M12*Assumptions!B20,0) -> 4491 | N21: =ROUND(N12*Assumptions!B20,0) -> 4490 | O21: =ROUND(O12*Assumptions!B20,0) -> 4515 | P21: =ROUND(P12*Assumptions!B20,0) -> 4567 | Q21: =ROUND(Q12*Assumptions!B20,0) -> 4643 | R21: =ROUND(R12*Assumptions!B20,0) -> 4739 | S21: =ROUND(S12*Assumptions!B20,0) -> 4857 | T21: =ROUND(T12*Assumptions!B20,0) -> 4993 | U21: =ROUND(U12*Assumptions!B20,0) -> 5150 | V21: =ROUND(V12*Assumptions!B20,0) -> 5324 | W21: =ROUND(W12*Assumptions!B20,0) -> 5517 | X21: =ROUND(X12*Assumptions!B20,0) -> 5729 | Y21: =ROUND(Y12*Assumptions!B20,0) -> 5959 | Z21: =ROUND(Z12*Assumptions!B20,0) -> 6208 | AA21: Var costs on Gross Revenue (accrual). B20.
A22: Tax Payment | B22: Cost | C22: =ROUND(Assumptions!B25*MAX(0,C12-(C15+C16+C17+C18+C19+C20+C21)),0) -> 2980 | D22: =ROUND(Assumptions!B25*MAX(0,D12-(D15+D16+D17+D18+D19+D20+D21)),0) -> 4627 | E22: =ROUND(Assumptions!B25*MAX(0,E12-(E15+E16+E17+E18+E19+E20+E21)),0) -> 6343 | F22: =ROUND(Assumptions!B25*MAX(0,F12-(F15+F16+F17+F18+F19+F20+F21)),0) -> 8058 | G22: =ROUND(Assumptions!B25*MAX(0,G12-(G15+G16+G17+G18+G19+G20+G21)),0) -> 9830 | H22: =ROUND(Assumptions!B25*MAX(0,H12-(H15+H16+H17+H18+H19+H20+H21)),0) -> 11682 | I22: =ROUND(Assumptions!B25*MAX(0,I12-(I15+I16+I17+I18+I19+I20+I21)),0) -> 10593 | J22: =ROUND(Assumptions!B25*MAX(0,J12-(J15+J16+J17+J18+J19+J20+J21)),0) -> 9755 | K22: =ROUND(Assumptions!B25*MAX(0,K12-(K15+K16+K17+K18+K19+K20+K21)),0) -> 5258 | L22: =ROUND(Assumptions!B25*MAX(0,L12-(L15+L16+L17+L18+L19+L20+L21)),0) -> 4873 | M22: =ROUND(Assumptions!B25*MAX(0,M12-(M15+M16+M17+M18+M19+M20+M21)),0) -> 4156 | N22: =ROUND(Assumptions!B25*MAX(0,N12-(N15+N16+N17+N18+N19+N20+N21)),0) -> 4143 | O22: =ROUND(Assumptions!B25*MAX(0,O12-(O15+O16+O17+O18+O19+O20+O21)),0) -> 4294 | P22: =ROUND(Assumptions!B25*MAX(0,P12-(P15+P16+P17+P18+P19+P20+P21)),0) -> 4607 | Q22: =ROUND(Assumptions!B25*MAX(0,Q12-(Q15+Q16+Q17+Q18+Q19+Q20+Q21)),0) -> 5064 | R22: =ROUND(Assumptions!B25*MAX(0,R12-(R15+R16+R17+R18+R19+R20+R21)),0) -> 5648 | S22: =ROUND(Assumptions!B25*MAX(0,S12-(S15+S16+S17+S18+S19+S20+S21)),0) -> 6363 | T22: =ROUND(Assumptions!B25*MAX(0,T12-(T15+T16+T17+T18+T19+T20+T21)),0) -> 7194 | U22: =ROUND(Assumptions!B25*MAX(0,U12-(U15+U16+U17+U18+U19+U20+U21)),0) -> 8147 | V22: =ROUND(Assumptions!B25*MAX(0,V12-(V15+V16+V17+V18+V19+V20+V21)),0) -> 9207 | W22: =ROUND(Assumptions!B25*MAX(0,W12-(W15+W16+W17+W18+W19+W20+W21)),0) -> 10382 | X22: =ROUND(Assumptions!B25*MAX(0,X12-(X15+X16+X17+X18+X19+X20+X21)),0) -> 11679 | Y22: =ROUND(Assumptions!B25*MAX(0,Y12-(Y15+Y16+Y17+Y18+Y19+Y20+Y21)),0) -> 13082 | Z22: =ROUND(Assumptions!B25*MAX(0,Z12-(Z15+Z16+Z17+Z18+Z19+Z20+Z21)),0) -> 14599 | AA22: Simplified: tax calculated on accrual-basis profit (Gross Revenue − OpCosts), not on cash received. Standard simplification for operational cash flow models. For pure cash-basis tax, link to actual tax payment schedule. B25.
A23: TOTAL OUTFLOW | B23: Cost | C23: =C15+C16+C17+C18+C19+C20+C21+C22 -> 108080 | D23: =D15+D16+D17+D18+D19+D20+D21+D22 -> 110016 | E23: =E15+E16+E17+E18+E19+E20+E21+E22 -> 112030 | F23: =F15+F16+F17+F18+F19+F20+F21+F22 -> 114385 | G23: =G15+G16+G17+G18+G19+G20+G21+G22 -> 116962 | H23: =H15+H16+H17+H18+H19+H20+H21+H22 -> 119657 | I23: =I15+I16+I17+I18+I19+I20+I21+I22 -> 118129 | J23: =J15+J16+J17+J18+J19+J20+J21+J22 -> 116962 | ... Z23: =Z15+Z16+Z17+Z18+Z19+Z20+Z21+Z22 -> 148522 | AA23: Payroll+Rent+SW+Infra+Support+Mktg+Var+Tax.
A24: ≡ NET CASH FLOW & BALANCE
A25: NET CASH FLOW | C25: =C13-C23+IF(Decisions!D11=1,IF(AND(ISNUMBER(Decisions!F11),INT(Decisions!F11)=Decisions!F11,Decisions!F11>=1,Decisions!F11<=24,1=Decisions!F11),Decisions!B11,0),0) -> -108080 | D25: =D13-D23+IF(Decisions!D11=1,IF(AND(ISNUMBER(Decisions!F11),INT(Decisions!F11)=Decisions!F11,Decisions!F11>=1,Decisions!F11<=24,2=Decisions!F11),Decisions!B11,0),0) -> 9984 | E25: =E13-E23+IF(Decisions!D11=1,IF(AND(ISNUMBER(Decisions!F11),INT(Decisions!F11)=Decisions!F11,Decisions!F11>=1,Decisions!F11<=24,3=Decisions!F11),Decisions!B11,0),0) -> 16495 | F25: =F13-F23+IF(Decisions!D11=1,IF(AND(ISNUMBER(Decisions!F11),INT(Decisions!F11)=Decisions!F11,Decisions!F11>=1,Decisions!F11<=24,4=Decisions!F11),Decisions!B11,0),0) -> 23016 | G25: =G13-G23+IF(Decisions!D11=1,IF(AND(ISNUMBER(Decisions!F11),INT(Decisions!F11)=Decisions!F11,Decisions!F11>=1,Decisions!F11<=24,5=Decisions!F11),Decisions!B11,0),0) -> 29654 | H25: =H13-H23+IF(Decisions!D11=1,IF(AND(ISNUMBER(Decisions!F11),INT(Decisions!F11)=Decisions!F11,Decisions!F11>=1,Decisions!F11<=24,6=Decisions!F11),Decisions!B11,0),0) -> 36626 | I25: =I13-I23+IF(Decisions!D11=1,IF(AND(ISNUMBER(Decisions!F11),INT(Decisions!F11)=Decisions!F11,Decisions!F11>=1,Decisions!F11<=24,7=Decisions!F11),Decisions!B11,0),0) -> 48258 | J25: =J13-J23+IF(Decisions!D11=1,IF(AND(ISNUMBER(Decisions!F11),INT(Decisions!F11)=Decisions!F11,Decisions!F11>=1,Decisions!F11<=24,8=Decisions!F11),Decisions!B11,0),0) -> 43539 | K25: =K13-K23+IF(Decisions!D11=1,IF(AND(ISNUMBER(Decisions!F11),INT(Decisions!F11)=Decisions!F11,Decisions!F11>=1,Decisions!F11<=24,9=Decisions!F11),Decisions!B11,0),0) -> 24239 | L25: =L13-L23+IF(Decisions!D11=1,IF(AND(ISNUMBER(Decisions!F11),INT(Decisions!F11)=Decisions!F11,Decisions!F11>=1,Decisions!F11<=24,10=Decisions!F11),Decisions!B11,0),0) -> 21546 | M25: =M13-M23+IF(Decisions!D11=1,IF(AND(ISNUMBER(Decisions!F11),INT(Decisions!F11)=Decisions!F11,Decisions!F11>=1,Decisions!F11<=24,11=Decisions!F11),Decisions!B11,0),0) -> 17661 | N25: =N13-N23+IF(Decisions!D11=1,IF(AND(ISNUMBER(Decisions!F11),INT(Decisions!F11)=Decisions!F11,Decisions!F11>=1,Decisions!F11<=24,12=Decisions!F11),Decisions!B11,0),0) -> 16606 | O25: =O13-O23+IF(Decisions!D11=1,IF(AND(ISNUMBER(Decisions!F11),INT(Decisions!F11)=Decisions!F11,Decisions!F11>=1,Decisions!F11<=24,13=Decisions!F11),Decisions!B11,0),0) -> 16323 | P25: =P13-P23+IF(Decisions!D11=1,IF(AND(ISNUMBER(Decisions!F11),INT(Decisions!F11)=Decisions!F11,Decisions!F11>=1,Decisions!F11<=24,14=Decisions!F11),Decisions!B11,0),0) -> 16689 | Q25: =Q13-Q23+IF(Decisions!D11=1,IF(AND(ISNUMBER(Decisions!F11),INT(Decisions!F11)=Decisions!F11,Decisions!F11>=1,Decisions!F11<=24,15=Decisions!F11),Decisions!B11,0),0) -> 17736 | R25: =R13-R23+IF(Decisions!D11=1,IF(AND(ISNUMBER(Decisions!F11),INT(Decisions!F11)=Decisions!F11,Decisions!F11>=1,Decisions!F11<=24,16=Decisions!F11),Decisions!B11,0),0) -> 19383 | S25: =S13-S23+IF(Decisions!D11=1,IF(AND(ISNUMBER(Decisions!F11),INT(Decisions!F11)=Decisions!F11,Decisions!F11>=1,Decisions!F11<=24,17=Decisions!F11),Decisions!B11,0),0) -> 21528 | T25: =T13-T23+IF(Decisions!D11=1,IF(AND(ISNUMBER(Decisions!F11),INT(Decisions!F11)=Decisions!F11,Decisions!F11>=1,Decisions!F11<=24,18=Decisions!F11),Decisions!B11,0),0) -> 24223 | U25: =U13-U23+IF(Decisions!D11=1,IF(AND(ISNUMBER(Decisions!F11),INT(Decisions!F11)=Decisions!F11,Decisions!F11>=1,Decisions!F11<=24,19=Decisions!F11),Decisions!B11,0),0) -> 27370 | V25: =V13-V23+IF(Decisions!D11=1,IF(AND(ISNUMBER(Decisions!F11),INT(Decisions!F11)=Decisions!F11,Decisions!F11>=1,Decisions!F11<=24,20=Decisions!F11),Decisions!B11,0),0) -> 31028 | W25: =W13-W23+IF(Decisions!D11=1,IF(AND(ISNUMBER(Decisions!F11),INT(Decisions!F11)=Decisions!F11,Decisions!F11>=1,Decisions!F11<=24,21=Decisions!F11),Decisions!B11,0),0) -> 35105 | X25: =X13-X23+IF(Decisions!D11=1,IF(AND(ISNUMBER(Decisions!F11),INT(Decisions!F11)=Decisions!F11,Decisions!F11>=1,Decisions!F11<=24,22=Decisions!F11),Decisions!B11,0),0) -> 39631 | Y25: =Y13-Y23+IF(Decisions!D11=1,IF(AND(ISNUMBER(Decisions!F11),INT(Decisions!F11)=Decisions!F11,Decisions!F11>=1,Decisions!F11<=24,23=Decisions!F11),Decisions!B11,0),0) -> 44664 | Z25: =Z13-Z23+IF(Decisions!D11=1,IF(AND(ISNUMBER(Decisions!F11),INT(Decisions!F11)=Decisions!F11,Decisions!F11>=1,Decisions!F11<=24,24=Decisions!F11),Decisions!B11,0),0) -> 50112 | AA25: Inflow − Outflow + Emergency Fundraise if D11=1 in month F11.
A26: CLOSING BALANCE | C26: =Assumptions!B34+C25 -> 391920 | D26: =C26+D25 -> 401904 | E26: =D26+E25 -> 418399 | F26: =E26+F25 -> 441415 | G26: =F26+G25 -> 471069 | H26: =G26+H25 -> 507695 | I26: =H26+I25 -> 555953 | J26: =I26+J25 -> 599492 | K26: =J26+K25 -> 623731 | ... Z26: =Y26+Z25 -> 1023336
A27: KPIs
A28: Burn Rate | B28: KPI | C28: =IF(C25<0,ABS(C25),0) -> 108080 | D28: =IF(D25<0,ABS(D25),0) -> 0 | E28: =IF(E25<0,ABS(E25),0) -> 0 | F28: =IF(F25<0,ABS(F25),0) -> 0 | G28: =IF(G25<0,ABS(G25),0) -> 0 | H28: =IF(H25<0,ABS(H25),0) -> 0 | I28: =IF(I25<0,ABS(I25),0) -> 0 | J28: =IF(J25<0,ABS(J25),0) -> 0 | ... Z28: =IF(Z25<0,ABS(Z25),0) -> 0 | AA28: ABS(NCF) when NCF negative, else 0.
A29: Runway (months) | B29: KPI | C29: =IF(C25<0,IF(C26<=0,"💀 Exhausted",IF(C28>0,ROUND(MAX(0,C26/C28),1),"N/A")),"✅ Safe") -> 3.6 | D29: =IF(D25<0,IF(D26<=0,"💀 Exhausted",IF(D28>0,ROUND(MAX(0,D26/D28),1),"N/A")),"✅ Safe") -> ✅ Safe | E29: =IF(E25<0,IF(E26<=0,"💀 Exhausted",IF(E28>0,ROUND(MAX(0,E26/E28),1),"N/A")),"✅ Safe") -> ✅ Safe | F29: =IF(F25<0,IF(F26<=0,"💀 Exhausted",IF(F28>0,ROUND(MAX(0,F26/F28),1),"N/A")),"✅ Safe") -> ✅ Safe | G29: =IF(G25<0,IF(G26<=0,"💀 Exhausted",IF(G28>0,ROUND(MAX(0,G26/G28),1),"N/A")),"✅ Safe") -> ✅ Safe | H29: =IF(H25<0,IF(H26<=0,"💀 Exhausted",IF(H28>0,ROUND(MAX(0,H26/H28),1),"N/A")),"✅ Safe") -> ✅ Safe | I29: =IF(I25<0,IF(I26<=0,"💀 Exhausted",IF(I28>0,ROUND(MAX(0,I26/I28),1),"N/A")),"✅ Safe") -> ✅ Safe | J29: =IF(J25<0,IF(J26<=0,"💀 Exhausted",IF(J28>0,ROUND(MAX(0,J26/J28),1),"N/A")),"✅ Safe") -> ✅ Safe | ... Z29: =IF(Z25<0,IF(Z26<=0,"💀 Exhausted",IF(Z28>0,ROUND(MAX(0,Z26/Z28),1),"N/A")),"✅ Safe") -> ✅ Safe | AA29: IF(NCF<0, MAX(0, Balance/BurnRate), "Safe"). "Exhausted" when balance≤0.
A30: Runway Alert | B30: KPI | C30: =IF(C29="💀 Exhausted","🔴 GONE",IF(ISNUMBER(C29),IF(C29<Assumptions!B41,"⚠ LOW","✅ OK"),"✅ OK")) -> ✅ OK | D30: =IF(D29="💀 Exhausted","🔴 GONE",IF(ISNUMBER(D29),IF(D29<Assumptions!B41,"⚠ LOW","✅ OK"),"✅ OK")) -> ✅ OK | E30: =IF(E29="💀 Exhausted","🔴 GONE",IF(ISNUMBER(E29),IF(E29<Assumptions!B41,"⚠ LOW","✅ OK"),"✅ OK")) -> ✅ OK | F30: =IF(F29="💀 Exhausted","🔴 GONE",IF(ISNUMBER(F29),IF(F29<Assumptions!B41,"⚠ LOW","✅ OK"),"✅ OK")) -> ✅ OK | G30: =IF(G29="💀 Exhausted","🔴 GONE",IF(ISNUMBER(G29),IF(G29<Assumptions!B41,"⚠ LOW","✅ OK"),"✅ OK")) -> ✅ OK | H30: =IF(H29="💀 Exhausted","🔴 GONE",IF(ISNUMBER(H29),IF(H29<Assumptions!B41,"⚠ LOW","✅ OK"),"✅ OK")) -> ✅ OK | I30: =IF(I29="💀 Exhausted","🔴 GONE",IF(ISNUMBER(I29),IF(I29<Assumptions!B41,"⚠ LOW","✅ OK"),"✅ OK")) -> ✅ OK | J30: =IF(J29="💀 Exhausted","🔴 GONE",IF(ISNUMBER(J29),IF(J29<Assumptions!B41,"⚠ LOW","✅ OK"),"✅ OK")) -> ✅ OK | K30: =IF(K29="💀 Exhausted","🔴 GONE",IF(ISNUMBER(K29),IF(K29<Assumptions!B41,"⚠ LOW","✅ OK"),"✅ OK")) -> ✅ OK | L30: =IF(L29="💀 Exhausted","🔴 GONE",IF(ISNUMBER(L29),IF(L29<Assumptions!B41,"⚠ LOW","✅ OK"),"✅ OK")) -> ✅ OK | M30: =IF(M29="💀 Exhausted","🔴 GONE",IF(ISNUMBER(M29),IF(M29<Assumptions!B41,"⚠ LOW","✅ OK"),"✅ OK")) -> ✅ OK | N30: =IF(N29="💀 Exhausted","🔴 GONE",IF(ISNUMBER(N29),IF(N29<Assumptions!B41,"⚠ LOW","✅ OK"),"✅ OK")) -> ✅ OK | O30: =IF(O29="💀 Exhausted","🔴 GONE",IF(ISNUMBER(O29),IF(O29<Assumptions!B41,"⚠ LOW","✅ OK"),"✅ OK")) -> ✅ OK | P30: =IF(P29="💀 Exhausted","🔴 GONE",IF(ISNUMBER(P29),IF(P29<Assumptions!B41,"⚠ LOW","✅ OK"),"✅ OK")) -> ✅ OK | Q30: =IF(Q29="💀 Exhausted","🔴 GONE",IF(ISNUMBER(Q29),IF(Q29<Assumptions!B41,"⚠ LOW","✅ OK"),"✅ OK")) -> ✅ OK | R30: =IF(R29="💀 Exhausted","🔴 GONE",IF(ISNUMBER(R29),IF(R29<Assumptions!B41,"⚠ LOW","✅ OK"),"✅ OK")) -> ✅ OK | S30: =IF(S29="💀 Exhausted","🔴 GONE",IF(ISNUMBER(S29),IF(S29<Assumptions!B41,"⚠ LOW","✅ OK"),"✅ OK")) -> ✅ OK | T30: =IF(T29="💀 Exhausted","🔴 GONE",IF(ISNUMBER(T29),IF(T29<Assumptions!B41,"⚠ LOW","✅ OK"),"✅ OK")) -> ✅ OK | U30: =IF(U29="💀 Exhausted","🔴 GONE",IF(ISNUMBER(U29),IF(U29<Assumptions!B41,"⚠ LOW","✅ OK"),"✅ OK")) -> ✅ OK | V30: =IF(V29="💀 Exhausted","🔴 GONE",IF(ISNUMBER(V29),IF(V29<Assumptions!B41,"⚠ LOW","✅ OK"),"✅ OK")) -> ✅ OK | W30: =IF(W29="💀 Exhausted","🔴 GONE",IF(ISNUMBER(W29),IF(W29<Assumptions!B41,"⚠ LOW","✅ OK"),"✅ OK")) -> ✅ OK | X30: =IF(X29="💀 Exhausted","🔴 GONE",IF(ISNUMBER(X29),IF(X29<Assumptions!B41,"⚠ LOW","✅ OK"),"✅ OK")) -> ✅ OK | Y30: =IF(Y29="💀 Exhausted","🔴 GONE",IF(ISNUMBER(Y29),IF(Y29<Assumptions!B41,"⚠ LOW","✅ OK"),"✅ OK")) -> ✅ OK | Z30: =IF(Z29="💀 Exhausted","🔴 GONE",IF(ISNUMBER(Z29),IF(Z29<Assumptions!B41,"⚠ LOW","✅ OK"),"✅ OK")) -> ✅ OK | AA30: ⚠ LOW when runway < threshold (Assumptions B41)
A31: Breakeven Revenue | B31: KPI | C31: =IFERROR((C23-C21-C22)/(1-Assumptions!B20),0) -> 104639.18 | D31: =IFERROR((D23-D21-D22)/(1-Assumptions!B20),0) -> 104673.2 | E31: =IFERROR((E23-E21-E22)/(1-Assumptions!B20),0) -> 104706.19 | F31: =IFERROR((F23-F21-F22)/(1-Assumptions!B20),0) -> 105081.44 | G31: =IFERROR((G23-G21-G22)/(1-Assumptions!B20),0) -> 105612.37 | H31: =IFERROR((H23-H21-H22)/(1-Assumptions!B20),0) -> 106168.04 | I31: =IFERROR((I23-I21-I22)/(1-Assumptions!B20),0) -> 105897.94 | J31: =IFERROR((J23-J21-J22)/(1-Assumptions!B20),0) -> 105698.97 | K31: =IFERROR((K23-K21-K22)/(1-Assumptions!B20),0) -> 125671.13 | L31: =IFERROR((L23-L21-L22)/(1-Assumptions!B20),0) -> 125600 | M31: =IFERROR((M23-M21-M22)/(1-Assumptions!B20),0) -> 128259.79 | N31: =IFERROR((N23-N21-N22)/(1-Assumptions!B20),0) -> 128293.81 | O31: =IFERROR((O23-O21-O22)/(1-Assumptions!B20),0) -> 128371.13 | P31: =IFERROR((P23-P21-P22)/(1-Assumptions!B20),0) -> 128495.88 | Q31: =IFERROR((Q23-Q21-Q22)/(1-Assumptions!B20),0) -> 128660.82 | R31: =IFERROR((R23-R21-R22)/(1-Assumptions!B20),0) -> 128860.82 | S31: =IFERROR((S23-S21-S22)/(1-Assumptions!B20),0) -> 129097.94 | T31: =IFERROR((T23-T21-T22)/(1-Assumptions!B20),0) -> 129367.01 | U31: =IFERROR((U23-U21-U22)/(1-Assumptions!B20),0) -> 129671.13 | V31: =IFERROR((V23-V21-V22)/(1-Assumptions!B20),0) -> 130005.15 | W31: =IFERROR((W23-W21-W22)/(1-Assumptions!B20),0) -> 130371.13 | X31: =IFERROR((X23-X21-X22)/(1-Assumptions!B20),0) -> 130772.16 | Y31: =IFERROR((Y23-Y21-Y22)/(1-Assumptions!B20),0) -> 131202.06 | Z31: =IFERROR((Z23-Z21-Z22)/(1-Assumptions!B20),0) -> 131664.95 | AA31: (Outflow − Var Costs − Tax) / (1 − Var_Pct). Pre-tax breakeven: fixed+semi-fixed costs only. Tax excluded from numerator (circular: profit needed to calculate tax). Ref B20.

Sheet Export_Data
A1: Date | B1: Category | C1: Sub-category | D1: Scenario_Name | E1: Value | F1: Month_Num | G1: Date_Full | H1: Sign
A2: 2025-01 | B2: Inflow | C2: Total Inflow | D2: =IF(SUMPRODUCT((Decisions!D4:D11=1)*1)=0,"Baseline",SUBSTITUTE(TRIM(IF(Decisions!D4=1,"CutMktg ","")&IF(Decisions!D5=1,"CutHead ","")&IF(Decisions!D6=1,"FrzHire ","")&IF(Decisions!D7=1,"PriceUp ","")&IF(Decisions!D8=1,"RetChurn ","")&IF(Decisions!D9=1,"KillInfra ","")&IF(Decisions!D10=1,"FastAR ","")&IF(Decisions!D11=1,"Fundraise",""))," ","+")) -> CutMktg+FrzHire | E2: ='Cash Flow Model'!C13 -> 0 | F2: 1 | G2: 2025-01-01 | H2: —
A3: 2025-02 | B3: Inflow | C3: Total Inflow | D3: =IF(SUMPRODUCT((Decisions!D4:D11=1)*1)=0,"Baseline",SUBSTITUTE(TRIM(IF(Decisions!D4=1,"CutMktg ","")&IF(Decisions!D5=1,"CutHead ","")&IF(Decisions!D6=1,"FrzHire ","")&IF(Decisions!D7=1,"PriceUp ","")&IF(Decisions!D8=1,"RetChurn ","")&IF(Decisions!D9=1,"KillInfra ","")&IF(Decisions!D10=1,"FastAR ","")&IF(Decisions!D11=1,"Fundraise",""))," ","+")) -> CutMktg+FrzHire | E3: ='Cash Flow Model'!D13 -> 120000 | F3: 2 | G3: 2025-02-01 | H3: —
A4: 2025-03 | B4: Inflow | C4: Total Inflow | D4: =IF(SUMPRODUCT((Decisions!D4:D11=1)*1)=0,"Baseline",SUBSTITUTE(TRIM(IF(Decisions!D4=1,"CutMktg ","")&IF(Decisions!D5=1,"CutHead ","")&IF(Decisions!D6=1,"FrzHire ","")&IF(Decisions!D7=1,"PriceUp ","")&IF(Decisions!D8=1,"RetChurn ","")&IF(Decisions!D9=1,"KillInfra ","")&IF(Decisions!D10=1,"FastAR ","")&IF(Decisions!D11=1,"Fundraise",""))," ","+")) -> CutMktg+FrzHire | E4: ='Cash Flow Model'!E13 -> 128525 | F4: 3 | G4: 2025-03-01 | H4: —
A5: 2025-04 | B5: Inflow | C5: Total Inflow | D5: =IF(SUMPRODUCT((Decisions!D4:D11=1)*1)=0,"Baseline",SUBSTITUTE(TRIM(IF(Decisions!D4=1,"CutMktg ","")&IF(Decisions!D5=1,"CutHead ","")&IF(Decisions!D6=1,"FrzHire ","")&IF(Decisions!D7=1,"PriceUp ","")&IF(Decisions!D8=1,"RetChurn ","")&IF(Decisions!D9=1,"KillInfra ","")&IF(Decisions!D10=1,"FastAR ","")&IF(Decisions!D11=1,"Fundraise",""))," ","+")) -> CutMktg+FrzHire | E5: ='Cash Flow Model'!F13 -> 137401 | F5: 4 | G5: 2025-04-01 | H5: —
A6: 2025-05 | B6: Inflow | C6: Total Inflow | D6: =IF(SUMPRODUCT((Decisions!D4:D11=1)*1)=0,"Baseline",SUBSTITUTE(TRIM(IF(Decisions!D4=1,"CutMktg ","")&IF(Decisions!D5=1,"CutHead ","")&IF(Decisions!D6=1,"FrzHire ","")&IF(Decisions!D7=1,"PriceUp ","")&IF(Decisions!D8=1,"RetChurn ","")&IF(Decisions!D9=1,"KillInfra ","")&IF(Decisions!D10=1,"FastAR ","")&IF(Decisions!D11=1,"Fundraise",""))," ","+")) -> CutMktg+FrzHire | E6: ='Cash Flow Model'!G13 -> 146616 | F6: 5 | G6: 2025-05-01 | H6: —
A7: 2025-06 | B7: Inflow | C7: Total Inflow | D7: =IF(SUMPRODUCT((Decisions!D4:D11=1)*1)=0,"Baseline",SUBSTITUTE(TRIM(IF(Decisions!D4=1,"CutMktg ","")&IF(Decisions!D5=1,"CutHead ","")&IF(Decisions!D6=1,"FrzHire ","")&IF(Decisions!D7=1,"PriceUp ","")&IF(Decisions!D8=1,"RetChurn ","")&IF(Decisions!D9=1,"KillInfra ","")&IF(Decisions!D10=1,"FastAR ","")&IF(Decisions!D11=1,"Fundraise",""))," ","+")) -> CutMktg+FrzHire | E7: ='Cash Flow Model'!H13 -> 156283 | F7: 6 | G7: 2025-06-01 | H7: —
A8: 2025-07 | B8: Inflow | C8: Total Inflow | D8: =IF(SUMPRODUCT((Decisions!D4:D11=1)*1)=0,"Baseline",SUBSTITUTE(TRIM(IF(Decisions!D4=1,"CutMktg ","")&IF(Decisions!D5=1,"CutHead ","")&IF(Decisions!D6=1,"FrzHire ","")&IF(Decisions!D7=1,"PriceUp ","")&IF(Decisions!D8=1,"RetChurn ","")&IF(Decisions!D9=1,"KillInfra ","")&IF(Decisions!D10=1,"FastAR ","")&IF(Decisions!D11=1,"Fundraise",""))," ","+")) -> CutMktg+FrzHire | E8: ='Cash Flow Model'!I13 -> 166387 | F8: 7 | G8: 2025-07-01 | H8: —
A9: 2025-08 | B9: Inflow | C9: Total Inflow | D9: =IF(SUMPRODUCT((Decisions!D4:D11=1)*1)=0,"Baseline",SUBSTITUTE(TRIM(IF(Decisions!D4=1,"CutMktg ","")&IF(Decisions!D5=1,"CutHead ","")&IF(Decisions!D6=1,"FrzHire ","")&IF(Decisions!D7=1,"PriceUp ","")&IF(Decisions!D8=1,"RetChurn ","")&IF(Decisions!D9=1,"KillInfra ","")&IF(Decisions!D10=1,"FastAR ","")&IF(Decisions!D11=1,"Fundraise",""))," ","+")) -> CutMktg+FrzHire | E9: ='Cash Flow Model'!J13 -> 160501 | F9: 8 | G9: 2025-08-01 | H9: —
A10: 2025-09 | B10: Inflow | C10: Total Inflow | D10: =IF(SUMPRODUCT((Decisions!D4:D11=1)*1)=0,"Baseline",SUBSTITUTE(TRIM(IF(Decisions!D4=1,"CutMktg ","")&IF(Decisions!D5=1,"CutHead ","")&IF(Decisions!D6=1,"FrzHire ","")&IF(Decisions!D7=1,"PriceUp ","")&IF(Decisions!D8=1,"RetChurn ","")&IF(Decisions!D9=1,"KillInfra ","")&IF(Decisions!D10=1,"FastAR ","")&IF(Decisions!D11=1,"Fundraise",""))," ","+")) -> CutMktg+FrzHire | E10: ='Cash Flow Model'!K13 -> 155981 | F10: 9 | G10: 2025-09-01 | H10: —
A11: 2025-10 | B11: Inflow | C11: Total Inflow | D11: =IF(SUMPRODUCT((Decisions!D4:D11=1)*1)=0,"Baseline",SUBSTITUTE(TRIM(IF(Decisions!D4=1,"CutMktg ","")&IF(Decisions!D5=1,"CutHead ","")&IF(Decisions!D6=1,"FrzHire ","")&IF(Decisions!D7=1,"PriceUp ","")&IF(Decisions!D8=1,"RetChurn ","")&IF(Decisions!D9=1,"KillInfra ","")&IF(Decisions!D10=1,"FastAR ","")&IF(Decisions!D11=1,"Fundraise",""))," ","+")) -> CutMktg+FrzHire | E11: ='Cash Flow Model'!L13 -> 152773 | F11: 10 | G11: 2025-10-01 | H11: —
A12: 2025-11 | B12: Inflow | C12: Total Inflow | D12: =IF(SUMPRODUCT((Decisions!D4:D11=1)*1)=0,"Baseline",SUBSTITUTE(TRIM(IF(Decisions!D4=1,"CutMktg ","")&IF(Decisions!D5=1,"CutHead ","")&IF(Decisions!D6=1,"FrzHire ","")&IF(Decisions!D7=1,"PriceUp ","")&IF(Decisions!D8=1,"RetChurn ","")&IF(Decisions!D9=1,"KillInfra ","")&IF(Decisions!D10=1,"FastAR ","")&IF(Decisions!D11=1,"Fundraise",""))," ","+")) -> CutMktg+FrzHire | E12: ='Cash Flow Model'!M13 -> 150720 | F12: 11 | G12: 2025-11-01 | H12: —
A13: 2025-12 | B13: Inflow | C13: Total Inflow | D13: =IF(SUMPRODUCT((Decisions!D4:D11=1)*1)=0,"Baseline",SUBSTITUTE(TRIM(IF(Decisions!D4=1,"CutMktg ","")&IF(Decisions!D5=1,"CutHead ","")&IF(Decisions!D6=1,"FrzHire ","")&IF(Decisions!D7=1,"PriceUp ","")&IF(Decisions!D8=1,"RetChurn ","")&IF(Decisions!D9=1,"KillInfra ","")&IF(Decisions!D10=1,"FastAR ","")&IF(Decisions!D11=1,"Fundraise",""))," ","+")) -> CutMktg+FrzHire | E13: ='Cash Flow Model'!N13 -> 149684 | F13: 12 | G13: 2025-12-01 | H13: —
A14: 2026-01 | B14: Inflow | C14: Total Inflow | D14: =IF(SUMPRODUCT((Decisions!D4:D11=1)*1)=0,"Baseline",SUBSTITUTE(TRIM(IF(Decisions!D4=1,"CutMktg ","")&IF(Decisions!D5=1,"CutHead ","")&IF(Decisions!D6=1,"FrzHire ","")&IF(Decisions!D7=1,"PriceUp ","")&IF(Decisions!D8=1,"RetChurn ","")&IF(Decisions!D9=1,"KillInfra ","")&IF(Decisions!D10=1,"FastAR ","")&IF(Decisions!D11=1,"Fundraise",""))," ","+")) -> CutMktg+FrzHire | E14: ='Cash Flow Model'!O13 -> 149652 | F14: 13 | G14: 2026-01-01 | H14: —
A15: 2026-02 | B15: Inflow | C15: Total Inflow | D15: =IF(SUMPRODUCT((Decisions!D4:D11=1)*1)=0,"Baseline",SUBSTITUTE(TRIM(IF(Decisions!D4=1,"CutMktg ","")&IF(Decisions!D5=1,"CutHead ","")&IF(Decisions!D6=1,"FrzHire ","")&IF(Decisions!D7=1,"PriceUp ","")&IF(Decisions!D8=1,"RetChurn ","")&IF(Decisions!D9=1,"KillInfra ","")&IF(Decisions!D10=1,"FastAR ","")&IF(Decisions!D11=1,"Fundraise",""))," ","+")) -> CutMktg+FrzHire | E15: ='Cash Flow Model'!P13 -> 150504 | F15: 14 | G15: 2026-02-01 | H15: —
A16: 2026-03 | B16: Inflow | C16: Total Inflow | D16: =IF(SUMPRODUCT((Decisions!D4:D11=1)*1)=0,"Baseline",SUBSTITUTE(TRIM(IF(Decisions!D4=1,"CutMktg ","")&IF(Decisions!D5=1,"CutHead ","")&IF(Decisions!D6=1,"FrzHire ","")&IF(Decisions!D7=1,"PriceUp ","")&IF(Decisions!D8=1,"RetChurn ","")&IF(Decisions!D9=1,"KillInfra ","")&IF(Decisions!D10=1,"FastAR ","")&IF(Decisions!D11=1,"Fundraise",""))," ","+")) -> CutMktg+FrzHire | E16: ='Cash Flow Model'!Q13 -> 152244 | F16: 15 | G16: 2026-03-01 | H16: —
A17: 2026-04 | B17: Inflow | C17: Total Inflow | D17: =IF(SUMPRODUCT((Decisions!D4:D11=1)*1)=0,"Baseline",SUBSTITUTE(TRIM(IF(Decisions!D4=1,"CutMktg ","")&IF(Decisions!D5=1,"CutHead ","")&IF(Decisions!D6=1,"FrzHire ","")&IF(Decisions!D7=1,"PriceUp ","")&IF(Decisions!D8=1,"RetChurn ","")&IF(Decisions!D9=1,"KillInfra ","")&IF(Decisions!D10=1,"FastAR ","")&IF(Decisions!D11=1,"Fundraise",""))," ","+")) -> CutMktg+FrzHire | E17: ='Cash Flow Model'!R13 -> 154765 | F17: 16 | G17: 2026-04-01 | H17: —
A18: 2026-05 | B18: Inflow | C18: Total Inflow | D18: =IF(SUMPRODUCT((Decisions!D4:D11=1)*1)=0,"Baseline",SUBSTITUTE(TRIM(IF(Decisions!D4=1,"CutMktg ","")&IF(Decisions!D5=1,"CutHead ","")&IF(Decisions!D6=1,"FrzHire ","")&IF(Decisions!D7=1,"PriceUp ","")&IF(Decisions!D8=1,"RetChurn ","")&IF(Decisions!D9=1,"KillInfra ","")&IF(Decisions!D10=1,"FastAR ","")&IF(Decisions!D11=1,"Fundraise",""))," ","+")) -> CutMktg+FrzHire | E18: ='Cash Flow Model'!S13 -> 157973 | F18: 17 | G18: 2026-05-01 | H18: —
A19: 2026-06 | B19: Inflow | C19: Total Inflow | D19: =IF(SUMPRODUCT((Decisions!D4:D11=1)*1)=0,"Baseline",SUBSTITUTE(TRIM(IF(Decisions!D4=1,"CutMktg ","")&IF(Decisions!D5=1,"CutHead ","")&IF(Decisions!D6=1,"FrzHire ","")&IF(Decisions!D7=1,"PriceUp ","")&IF(Decisions!D8=1,"RetChurn ","")&IF(Decisions!D9=1,"KillInfra ","")&IF(Decisions!D10=1,"FastAR ","")&IF(Decisions!D11=1,"Fundraise",""))," ","+")) -> CutMktg+FrzHire | E19: ='Cash Flow Model'!T13 -> 161896 | F19: 18 | G19: 2026-06-01 | H19: —
A20: 2026-07 | B20: Inflow | C20: Total Inflow | D20: =IF(SUMPRODUCT((Decisions!D4:D11=1)*1)=0,"Baseline",SUBSTITUTE(TRIM(IF(Decisions!D4=1,"CutMktg ","")&IF(Decisions!D5=1,"CutHead ","")&IF(Decisions!D6=1,"FrzHire ","")&IF(Decisions!D7=1,"PriceUp ","")&IF(Decisions!D8=1,"RetChurn ","")&IF(Decisions!D9=1,"KillInfra ","")&IF(Decisions!D10=1,"FastAR ","")&IF(Decisions!D11=1,"Fundraise",""))," ","+")) -> CutMktg+FrzHire | E20: ='Cash Flow Model'!U13 -> 166448 | F20: 19 | G20: 2026-07-01 | H20: —
A21: 2026-08 | B21: Inflow | C21: Total Inflow | D21: =IF(SUMPRODUCT((Decisions!D4:D11=1)*1)=0,"Baseline",SUBSTITUTE(TRIM(IF(Decisions!D4=1,"CutMktg ","")&IF(Decisions!D5=1,"CutHead ","")&IF(Decisions!D6=1,"FrzHire ","")&IF(Decisions!D7=1,"PriceUp ","")&IF(Decisions!D8=1,"RetChurn ","")&IF(Decisions!D9=1,"KillInfra ","")&IF(Decisions!D10=1,"FastAR ","")&IF(Decisions!D11=1,"Fundraise",""))," ","+")) -> CutMktg+FrzHire | E21: ='Cash Flow Model'!V13 -> 171664 | F21: 20 | G21: 2026-08-01 | H21: —
A22: 2026-09 | B22: Inflow | C22: Total Inflow | D22: =IF(SUMPRODUCT((Decisions!D4:D11=1)*1)=0,"Baseline",SUBSTITUTE(TRIM(IF(Decisions!D4=1,"CutMktg ","")&IF(Decisions!D5=1,"CutHead ","")&IF(Decisions!D6=1,"FrzHire ","")&IF(Decisions!D7=1,"PriceUp ","")&IF(Decisions!D8=1,"RetChurn ","")&IF(Decisions!D9=1,"KillInfra ","")&IF(Decisions!D10=1,"FastAR ","")&IF(Decisions!D11=1,"Fundraise",""))," ","+")) -> CutMktg+FrzHire | E22: ='Cash Flow Model'!W13 -> 177464 | F22: 21 | G22: 2026-09-01 | H22: —
A23: 2026-10 | B23: Inflow | C23: Total Inflow | D23: =IF(SUMPRODUCT((Decisions!D4:D11=1)*1)=0,"Baseline",SUBSTITUTE(TRIM(IF(Decisions!D4=1,"CutMktg ","")&IF(Decisions!D5=1,"CutHead ","")&IF(Decisions!D6=1,"FrzHire ","")&IF(Decisions!D7=1,"PriceUp ","")&IF(Decisions!D8=1,"RetChurn ","")&IF(Decisions!D9=1,"KillInfra ","")&IF(Decisions!D10=1,"FastAR ","")&IF(Decisions!D11=1,"Fundraise",""))," ","+")) -> CutMktg+FrzHire | E23: ='Cash Flow Model'!X13 -> 183888 | F23: 22 | G23: 2026-10-01 | H23: —
A24: 2026-11 | B24: Inflow | C24: Total Inflow | D24: =IF(SUMPRODUCT((Decisions!D4:D11=1)*1)=0,"Baseline",SUBSTITUTE(TRIM(IF(Decisions!D4=1,"CutMktg ","")&IF(Decisions!D5=1,"CutHead ","")&IF(Decisions!D6=1,"FrzHire ","")&IF(Decisions!D7=1,"PriceUp ","")&IF(Decisions!D8=1,"RetChurn ","")&IF(Decisions!D9=1,"KillInfra ","")&IF(Decisions!D10=1,"FastAR ","")&IF(Decisions!D11=1,"Fundraise",""))," ","+")) -> CutMktg+FrzHire | E24: ='Cash Flow Model'!Y13 -> 190971 | F24: 23 | G24: 2026-11-01 | H24: —
A25: 2026-12 | B25: Inflow | C25: Total Inflow | D25: =IF(SUMPRODUCT((Decisions!D4:D11=1)*1)=0,"Baseline",SUBSTITUTE(TRIM(IF(Decisions!D4=1,"CutMktg ","")&IF(Decisions!D5=1,"CutHead ","")&IF(Decisions!D6=1,"FrzHire ","")&IF(Decisions!D7=1,"PriceUp ","")&IF(Decisions!D8=1,"RetChurn ","")&IF(Decisions!D9=1,"KillInfra ","")&IF(Decisions!D10=1,"FastAR ","")&IF(Decisions!D11=1,"Fundraise",""))," ","+")) -> CutMktg+FrzHire | E25: ='Cash Flow Model'!Z13 -> 198634 | F25: 24 | G25: 2026-12-01 | H25: —
A26: 2025-01 | B26: Outflow | C26: Total Outflow | D26: =IF(SUMPRODUCT((Decisions!D4:D11=1)*1)=0,"Baseline",SUBSTITUTE(TRIM(IF(Decisions!D4=1,"CutMktg ","")&IF(Decisions!D5=1,"CutHead ","")&IF(Decisions!D6=1,"FrzHire ","")&IF(Decisions!D7=1,"PriceUp ","")&IF(Decisions!D8=1,"RetChurn ","")&IF(Decisions!D9=1,"KillInfra ","")&IF(Decisions!D10=1,"FastAR ","")&IF(Decisions!D11=1,"Fundraise",""))," ","+")) -> CutMktg+FrzHire | E26: ='Cash Flow Model'!C23 -> 108080 | F26: 1 | G26: 2025-01-01 | H26: —
A27: 2025-02 | B27: Outflow | C27: Total Outflow | D27: =IF(SUMPRODUCT((Decisions!D4:D11=1)*1)=0,"Baseline",SUBSTITUTE(TRIM(IF(Decisions!D4=1,"CutMktg ","")&IF(Decisions!D5=1,"CutHead ","")&IF(Decisions!D6=1,"FrzHire ","")&IF(Decisions!D7=1,"PriceUp ","")&IF(Decisions!D8=1,"RetChurn ","")&IF(Decisions!D9=1,"KillInfra ","")&IF(Decisions!D10=1,"FastAR ","")&IF(Decisions!D11=1,"Fundraise",""))," ","+")) -> CutMktg+FrzHire | E27: ='Cash Flow Model'!D23 -> 110016 | F27: 2 | G27: 2025-02-01 | H27: —
A28: 2025-03 | B28: Outflow | C28: Total Outflow | D28: =IF(SUMPRODUCT((Decisions!D4:D11=1)*1)=0,"Baseline",SUBSTITUTE(TRIM(IF(Decisions!D4=1,"CutMktg ","")&IF(Decisions!D5=1,"CutHead ","")&IF(Decisions!D6=1,"FrzHire ","")&IF(Decisions!D7=1,"PriceUp ","")&IF(Decisions!D8=1,"RetChurn ","")&IF(Decisions!D9=1,"KillInfra ","")&IF(Decisions!D10=1,"FastAR ","")&IF(Decisions!D11=1,"Fundraise",""))," ","+")) -> CutMktg+FrzHire | E28: ='Cash Flow Model'!E23 -> 112030 | F28: 3 | G28: 2025-03-01 | H28: —
A29: 2025-04 | B29: Outflow | C29: Total Outflow | D29: =IF(SUMPRODUCT((Decisions!D4:D11=1)*1)=0,"Baseline",SUBSTITUTE(TRIM(IF(Decisions!D4=1,"CutMktg ","")&IF(Decisions!D5=1,"CutHead ","")&IF(Decisions!D6=1,"FrzHire ","")&IF(Decisions!D7=1,"PriceUp ","")&IF(Decisions!D8=1,"RetChurn ","")&IF(Decisions!D9=1,"KillInfra ","")&IF(Decisions!D10=1,"FastAR ","")&IF(Decisions!D11=1,"Fundraise",""))," ","+")) -> CutMktg+FrzHire | E29: ='Cash Flow Model'!F23 -> 114385 | F29: 4 | G29: 2025-04-01 | H29: —
A30: 2025-05 | B30: Outflow | C30: Total Outflow | D30: =IF(SUMPRODUCT((Decisions!D4:D11=1)*1)=0,"Baseline",SUBSTITUTE(TRIM(IF(Decisions!D4=1,"CutMktg ","")&IF(Decisions!D5=1,"CutHead ","")&IF(Decisions!D6=1,"FrzHire ","")&IF(Decisions!D7=1,"PriceUp ","")&IF(Decisions!D8=1,"RetChurn ","")&IF(Decisions!D9=1,"KillInfra ","")&IF(Decisions!D10=1,"FastAR ","")&IF(Decisions!D11=1,"Fundraise",""))," ","+")) -> CutMktg+FrzHire | E30: ='Cash Flow Model'!G23 -> 116962 | F30: 5 | G30: 2025-05-01 | H30: —
A31: 2025-06 | B31: Outflow | C31: Total Outflow | D31: =IF(SUMPRODUCT((Decisions!D4:D11=1)*1)=0,"Baseline",SUBSTITUTE(TRIM(IF(Decisions!D4=1,"CutMktg ","")&IF(Decisions!D5=1,"CutHead ","")&IF(Decisions!D6=1,"FrzHire ","")&IF(Decisions!D7=1,"PriceUp ","")&IF(Decisions!D8=1,"RetChurn ","")&IF(Decisions!D9=1,"KillInfra ","")&IF(Decisions!D10=1,"FastAR ","")&IF(Decisions!D11=1,"Fundraise",""))," ","+")) -> CutMktg+FrzHire | E31: ='Cash Flow Model'!H23 -> 119657 | F31: 6 | G31: 2025-06-01 | H31: —
A32: 2025-07 | B32: Outflow | C32: Total Outflow | D32: =IF(SUMPRODUCT((Decisions!D4:D11=1)*1)=0,"Baseline",SUBSTITUTE(TRIM(IF(Decisions!D4=1,"CutMktg ","")&IF(Decisions!D5=1,"CutHead ","")&IF(Decisions!D6=1,"FrzHire ","")&IF(Decisions!D7=1,"PriceUp ","")&IF(Decisions!D8=1,"RetChurn ","")&IF(Decisions!D9=1,"KillInfra ","")&IF(Decisions!D10=1,"FastAR ","")&IF(Decisions!D11=1,"Fundraise",""))," ","+")) -> CutMktg+FrzHire | E32: ='Cash Flow Model'!I23 -> 118129 | F32: 7 | G32: 2025-07-01 | H32: —
A33: 2025-08 | B33: Outflow | C33: Total Outflow | D33: =IF(SUMPRODUCT((Decisions!D4:D11=1)*1)=0,"Baseline",SUBSTITUTE(TRIM(IF(Decisions!D4=1,"CutMktg ","")&IF(Decisions!D5=1,"CutHead ","")&IF(Decisions!D6=1,"FrzHire ","")&IF(Decisions!D7=1,"PriceUp ","")&IF(Decisions!D8=1,"RetChurn ","")&IF(Decisions!D9=1,"KillInfra ","")&IF(Decisions!D10=1,"FastAR ","")&IF(Decisions!D11=1,"Fundraise",""))," ","+")) -> CutMktg+FrzHire | E33: ='Cash Flow Model'!J23 -> 116962 | F33: 8 | G33: 2025-08-01 | H33: —
A34: 2025-09 | B34: Outflow | C34: Total Outflow | D34: =IF(SUMPRODUCT((Decisions!D4:D11=1)*1)=0,"Baseline",SUBSTITUTE(TRIM(IF(Decisions!D4=1,"CutMktg ","")&IF(Decisions!D5=1,"CutHead ","")&IF(Decisions!D6=1,"FrzHire ","")&IF(Decisions!D7=1,"PriceUp ","")&IF(Decisions!D8=1,"RetChurn ","")&IF(Decisions!D9=1,"KillInfra ","")&IF(Decisions!D10=1,"FastAR ","")&IF(Decisions!D11=1,"Fundraise",""))," ","+")) -> CutMktg+FrzHire | E34: ='Cash Flow Model'!K23 -> 131742 | F34: 9 | G34: 2025-09-01 | H34: —
A35: 2025-10 | B35: Outflow | C35: Total Outflow | D35: =IF(SUMPRODUCT((Decisions!D4:D11=1)*1)=0,"Baseline",SUBSTITUTE(TRIM(IF(Decisions!D4=1,"CutMktg ","")&IF(Decisions!D5=1,"CutHead ","")&IF(Decisions!D6=1,"FrzHire ","")&IF(Decisions!D7=1,"PriceUp ","")&IF(Decisions!D8=1,"RetChurn ","")&IF(Decisions!D9=1,"KillInfra ","")&IF(Decisions!D10=1,"FastAR ","")&IF(Decisions!D11=1,"Fundraise",""))," ","+")) -> CutMktg+FrzHire | E35: ='Cash Flow Model'!L23 -> 131227 | F35: 10 | G35: 2025-10-01 | H35: —
A36: 2025-11 | B36: Outflow | C36: Total Outflow | D36: =IF(SUMPRODUCT((Decisions!D4:D11=1)*1)=0,"Baseline",SUBSTITUTE(TRIM(IF(Decisions!D4=1,"CutMktg ","")&IF(Decisions!D5=1,"CutHead ","")&IF(Decisions!D6=1,"FrzHire ","")&IF(Decisions!D7=1,"PriceUp ","")&IF(Decisions!D8=1,"RetChurn ","")&IF(Decisions!D9=1,"KillInfra ","")&IF(Decisions!D10=1,"FastAR ","")&IF(Decisions!D11=1,"Fundraise",""))," ","+")) -> CutMktg+FrzHire | E36: ='Cash Flow Model'!M23 -> 133059 | F36: 11 | G36: 2025-11-01 | H36: —
A37: 2025-12 | B37: Outflow | C37: Total Outflow | D37: =IF(SUMPRODUCT((Decisions!D4:D11=1)*1)=0,"Baseline",SUBSTITUTE(TRIM(IF(Decisions!D4=1,"CutMktg ","")&IF(Decisions!D5=1,"CutHead ","")&IF(Decisions!D6=1,"FrzHire ","")&IF(Decisions!D7=1,"PriceUp ","")&IF(Decisions!D8=1,"RetChurn ","")&IF(Decisions!D9=1,"KillInfra ","")&IF(Decisions!D10=1,"FastAR ","")&IF(Decisions!D11=1,"Fundraise",""))," ","+")) -> CutMktg+FrzHire | E37: ='Cash Flow Model'!N23 -> 133078 | F37: 12 | G37: 2025-12-01 | H37: —
A38: 2026-01 | B38: Outflow | C38: Total Outflow | D38: =IF(SUMPRODUCT((Decisions!D4:D11=1)*1)=0,"Baseline",SUBSTITUTE(TRIM(IF(Decisions!D4=1,"CutMktg ","")&IF(Decisions!D5=1,"CutHead ","")&IF(Decisions!D6=1,"FrzHire ","")&IF(Decisions!D7=1,"PriceUp ","")&IF(Decisions!D8=1,"RetChurn ","")&IF(Decisions!D9=1,"KillInfra ","")&IF(Decisions!D10=1,"FastAR ","")&IF(Decisions!D11=1,"Fundraise",""))," ","+")) -> CutMktg+FrzHire | E38: ='Cash Flow Model'!O23 -> 133329 | F38: 13 | G38: 2026-01-01 | H38: —
A39: 2026-02 | B39: Outflow | C39: Total Outflow | D39: =IF(SUMPRODUCT((Decisions!D4:D11=1)*1)=0,"Baseline",SUBSTITUTE(TRIM(IF(Decisions!D4=1,"CutMktg ","")&IF(Decisions!D5=1,"CutHead ","")&IF(Decisions!D6=1,"FrzHire ","")&IF(Decisions!D7=1,"PriceUp ","")&IF(Decisions!D8=1,"RetChurn ","")&IF(Decisions!D9=1,"KillInfra ","")&IF(Decisions!D10=1,"FastAR ","")&IF(Decisions!D11=1,"Fundraise",""))," ","+")) -> CutMktg+FrzHire | E39: ='Cash Flow Model'!P23 -> 133815 | F39: 14 | G39: 2026-02-01 | H39: —
A40: 2026-03 | B40: Outflow | C40: Total Outflow | D40: =IF(SUMPRODUCT((Decisions!D4:D11=1)*1)=0,"Baseline",SUBSTITUTE(TRIM(IF(Decisions!D4=1,"CutMktg ","")&IF(Decisions!D5=1,"CutHead ","")&IF(Decisions!D6=1,"FrzHire ","")&IF(Decisions!D7=1,"PriceUp ","")&IF(Decisions!D8=1,"RetChurn ","")&IF(Decisions!D9=1,"KillInfra ","")&IF(Decisions!D10=1,"FastAR ","")&IF(Decisions!D11=1,"Fundraise",""))," ","+")) -> CutMktg+FrzHire | E40: ='Cash Flow Model'!Q23 -> 134508 | F40: 15 | G40: 2026-03-01 | H40: —
A41: 2026-04 | B41: Outflow | C41: Total Outflow | D41: =IF(SUMPRODUCT((Decisions!D4:D11=1)*1)=0,"Baseline",SUBSTITUTE(TRIM(IF(Decisions!D4=1,"CutMktg ","")&IF(Decisions!D5=1,"CutHead ","")&IF(Decisions!D6=1,"FrzHire ","")&IF(Decisions!D7=1,"PriceUp ","")&IF(Decisions!D8=1,"RetChurn ","")&IF(Decisions!D9=1,"KillInfra ","")&IF(Decisions!D10=1,"FastAR ","")&IF(Decisions!D11=1,"Fundraise",""))," ","+")) -> CutMktg+FrzHire | E41: ='Cash Flow Model'!R23 -> 135382 | F41: 16 | G41: 2026-04-01 | H41: —
A42: 2026-05 | B42: Outflow | C42: Total Outflow | D42: =IF(SUMPRODUCT((Decisions!D4:D11=1)*1)=0,"Baseline",SUBSTITUTE(TRIM(IF(Decisions!D4=1,"CutMktg ","")&IF(Decisions!D5=1,"CutHead ","")&IF(Decisions!D6=1,"FrzHire ","")&IF(Decisions!D7=1,"PriceUp ","")&IF(Decisions!D8=1,"RetChurn ","")&IF(Decisions!D9=1,"KillInfra ","")&IF(Decisions!D10=1,"FastAR ","")&IF(Decisions!D11=1,"Fundraise",""))," ","+")) -> CutMktg+FrzHire | E42: ='Cash Flow Model'!S23 -> 136445 | F42: 17 | G42: 2026-05-01 | H42: —
A43: 2026-06 | B43: Outflow | C43: Total Outflow | D43: =IF(SUMPRODUCT((Decisions!D4:D11=1)*1)=0,"Baseline",SUBSTITUTE(TRIM(IF(Decisions!D4=1,"CutMktg ","")&IF(Decisions!D5=1,"CutHead ","")&IF(Decisions!D6=1,"FrzHire ","")&IF(Decisions!D7=1,"PriceUp ","")&IF(Decisions!D8=1,"RetChurn ","")&IF(Decisions!D9=1,"KillInfra ","")&IF(Decisions!D10=1,"FastAR ","")&IF(Decisions!D11=1,"Fundraise",""))," ","+")) -> CutMktg+FrzHire | E43: ='Cash Flow Model'!T23 -> 137673 | F43: 18 | G43: 2026-06-01 | H43: —
A44: 2026-07 | B44: Outflow | C44: Total Outflow | D44: =IF(SUMPRODUCT((Decisions!D4:D11=1)*1)=0,"Baseline",SUBSTITUTE(TRIM(IF(Decisions!D4=1,"CutMktg ","")&IF(Decisions!D5=1,"CutHead ","")&IF(Decisions!D6=1,"FrzHire ","")&IF(Decisions!D7=1,"PriceUp ","")&IF(Decisions!D8=1,"RetChurn ","")&IF(Decisions!D9=1,"KillInfra ","")&IF(Decisions!D10=1,"FastAR ","")&IF(Decisions!D11=1,"Fundraise",""))," ","+")) -> CutMktg+FrzHire | E44: ='Cash Flow Model'!U23 -> 139078 | F44: 19 | G44: 2026-07-01 | H44: —
A45: 2026-08 | B45: Outflow | C45: Total Outflow | D45: =IF(SUMPRODUCT((Decisions!D4:D11=1)*1)=0,"Baseline",SUBSTITUTE(TRIM(IF(Decisions!D4=1,"CutMktg ","")&IF(Decisions!D5=1,"CutHead ","")&IF(Decisions!D6=1,"FrzHire ","")&IF(Decisions!D7=1,"PriceUp ","")&IF(Decisions!D8=1,"RetChurn ","")&IF(Decisions!D9=1,"KillInfra ","")&IF(Decisions!D10=1,"FastAR ","")&IF(Decisions!D11=1,"Fundraise",""))," ","+")) -> CutMktg+FrzHire | E45: ='Cash Flow Model'!V23 -> 140636 | F45: 20 | G45: 2026-08-01 | H45: —
A46: 2026-09 | B46: Outflow | C46: Total Outflow | D46: =IF(SUMPRODUCT((Decisions!D4:D11=1)*1)=0,"Baseline",SUBSTITUTE(TRIM(IF(Decisions!D4=1,"CutMktg ","")&IF(Decisions!D5=1,"CutHead ","")&IF(Decisions!D6=1,"FrzHire ","")&IF(Decisions!D7=1,"PriceUp ","")&IF(Decisions!D8=1,"RetChurn ","")&IF(Decisions!D9=1,"KillInfra ","")&IF(Decisions!D10=1,"FastAR ","")&IF(Decisions!D11=1,"Fundraise",""))," ","+")) -> CutMktg+FrzHire | E46: ='Cash Flow Model'!W23 -> 142359 | F46: 21 | G46: 2026-09-01 | H46: —
A47: 2026-10 | B47: Outflow | C47: Total Outflow | D47: =IF(SUMPRODUCT((Decisions!D4:D11=1)*1)=0,"Baseline",SUBSTITUTE(TRIM(IF(Decisions!D4=1,"CutMktg ","")&IF(Decisions!D5=1,"CutHead ","")&IF(Decisions!D6=1,"FrzHire ","")&IF(Decisions!D7=1,"PriceUp ","")&IF(Decisions!D8=1,"RetChurn ","")&IF(Decisions!D9=1,"KillInfra ","")&IF(Decisions!D10=1,"FastAR ","")&IF(Decisions!D11=1,"Fundraise",""))," ","+")) -> CutMktg+FrzHire | E47: ='Cash Flow Model'!X23 -> 144257 | F47: 22 | G47: 2026-10-01 | H47: —
A48: 2026-11 | B48: Outflow | C48: Total Outflow | D48: =IF(SUMPRODUCT((Decisions!D4:D11=1)*1)=0,"Baseline",SUBSTITUTE(TRIM(IF(Decisions!D4=1,"CutMktg ","")&IF(Decisions!D5=1,"CutHead ","")&IF(Decisions!D6=1,"FrzHire ","")&IF(Decisions!D7=1,"PriceUp ","")&IF(Decisions!D8=1,"RetChurn ","")&IF(Decisions!D9=1,"KillInfra ","")&IF(Decisions!D10=1,"FastAR ","")&IF(Decisions!D11=1,"Fundraise",""))," ","+")) -> CutMktg+FrzHire | E48: ='Cash Flow Model'!Y23 -> 146307 | F48: 23 | G48: 2026-11-01 | H48: —
A49: 2026-12 | B49: Outflow | C49: Total Outflow | D49: =IF(SUMPRODUCT((Decisions!D4:D11=1)*1)=0,"Baseline",SUBSTITUTE(TRIM(IF(Decisions!D4=1,"CutMktg ","")&IF(Decisions!D5=1,"CutHead ","")&IF(Decisions!D6=1,"FrzHire ","")&IF(Decisions!D7=1,"PriceUp ","")&IF(Decisions!D8=1,"RetChurn ","")&IF(Decisions!D9=1,"KillInfra ","")&IF(Decisions!D10=1,"FastAR ","")&IF(Decisions!D11=1,"Fundraise",""))," ","+")) -> CutMktg+FrzHire | E49: ='Cash Flow Model'!Z23 -> 148522 | F49: 24 | G49: 2026-12-01 | H49: —
A50: 2025-01 | B50: Net | C50: Net Cash Flow | D50: =IF(SUMPRODUCT((Decisions!D4:D11=1)*1)=0,"Baseline",SUBSTITUTE(TRIM(IF(Decisions!D4=1,"CutMktg ","")&IF(Decisions!D5=1,"CutHead ","")&IF(Decisions!D6=1,"FrzHire ","")&IF(Decisions!D7=1,"PriceUp ","")&IF(Decisions!D8=1,"RetChurn ","")&IF(Decisions!D9=1,"KillInfra ","")&IF(Decisions!D10=1,"FastAR ","")&IF(Decisions!D11=1,"Fundraise",""))," ","+")) -> CutMktg+FrzHire | E50: ='Cash Flow Model'!C25 -> -108080 | F50: 1 | G50: 2025-01-01 | H50: —
A51: 2025-02 | B51: Net | C51: Net Cash Flow | D51: =IF(SUMPRODUCT((Decisions!D4:D11=1)*1)=0,"Baseline",SUBSTITUTE(TRIM(IF(Decisions!D4=1,"CutMktg ","")&IF(Decisions!D5=1,"CutHead ","")&IF(Decisions!D6=1,"FrzHire ","")&IF(Decisions!D7=1,"PriceUp ","")&IF(Decisions!D8=1,"RetChurn ","")&IF(Decisions!D9=1,"KillInfra ","")&IF(Decisions!D10=1,"FastAR ","")&IF(Decisions!D11=1,"Fundraise",""))," ","+")) -> CutMktg+FrzHire | E51: ='Cash Flow Model'!D25 -> 9984 | F51: 2 | G51: 2025-02-01 | H51: —
A52: 2025-03 | B52: Net | C52: Net Cash Flow | D52: =IF(SUMPRODUCT((Decisions!D4:D11=1)*1)=0,"Baseline",SUBSTITUTE(TRIM(IF(Decisions!D4=1,"CutMktg ","")&IF(Decisions!D5=1,"CutHead ","")&IF(Decisions!D6=1,"FrzHire ","")&IF(Decisions!D7=1,"PriceUp ","")&IF(Decisions!D8=1,"RetChurn ","")&IF(Decisions!D9=1,"KillInfra ","")&IF(Decisions!D10=1,"FastAR ","")&IF(Decisions!D11=1,"Fundraise",""))," ","+")) -> CutMktg+FrzHire | E52: ='Cash Flow Model'!E25 -> 16495 | F52: 3 | G52: 2025-03-01 | H52: —
A53: 2025-04 | B53: Net | C53: Net Cash Flow | D53: =IF(SUMPRODUCT((Decisions!D4:D11=1)*1)=0,"Baseline",SUBSTITUTE(TRIM(IF(Decisions!D4=1,"CutMktg ","")&IF(Decisions!D5=1,"CutHead ","")&IF(Decisions!D6=1,"FrzHire ","")&IF(Decisions!D7=1,"PriceUp ","")&IF(Decisions!D8=1,"RetChurn ","")&IF(Decisions!D9=1,"KillInfra ","")&IF(Decisions!D10=1,"FastAR ","")&IF(Decisions!D11=1,"Fundraise",""))," ","+")) -> CutMktg+FrzHire | E53: ='Cash Flow Model'!F25 -> 23016 | F53: 4 | G53: 2025-04-01 | H53: —
A54: 2025-05 | B54: Net | C54: Net Cash Flow | D54: =IF(SUMPRODUCT((Decisions!D4:D11=1)*1)=0,"Baseline",SUBSTITUTE(TRIM(IF(Decisions!D4=1,"CutMktg ","")&IF(Decisions!D5=1,"CutHead ","")&IF(Decisions!D6=1,"FrzHire ","")&IF(Decisions!D7=1,"PriceUp ","")&IF(Decisions!D8=1,"RetChurn ","")&IF(Decisions!D9=1,"KillInfra ","")&IF(Decisions!D10=1,"FastAR ","")&IF(Decisions!D11=1,"Fundraise",""))," ","+")) -> CutMktg+FrzHire | E54: ='Cash Flow Model'!G25 -> 29654 | F54: 5 | G54: 2025-05-01 | H54: —
A55: 2025-06 | B55: Net | C55: Net Cash Flow | D55: =IF(SUMPRODUCT((Decisions!D4:D11=1)*1)=0,"Baseline",SUBSTITUTE(TRIM(IF(Decisions!D4=1,"CutMktg ","")&IF(Decisions!D5=1,"CutHead ","")&IF(Decisions!D6=1,"FrzHire ","")&IF(Decisions!D7=1,"PriceUp ","")&IF(Decisions!D8=1,"RetChurn ","")&IF(Decisions!D9=1,"KillInfra ","")&IF(Decisions!D10=1,"FastAR ","")&IF(Decisions!D11=1,"Fundraise",""))," ","+")) -> CutMktg+FrzHire | E55: ='Cash Flow Model'!H25 -> 36626 | F55: 6 | G55: 2025-06-01 | H55: —
A56: 2025-07 | B56: Net | C56: Net Cash Flow | D56: =IF(SUMPRODUCT((Decisions!D4:D11=1)*1)=0,"Baseline",SUBSTITUTE(TRIM(IF(Decisions!D4=1,"CutMktg ","")&IF(Decisions!D5=1,"CutHead ","")&IF(Decisions!D6=1,"FrzHire ","")&IF(Decisions!D7=1,"PriceUp ","")&IF(Decisions!D8=1,"RetChurn ","")&IF(Decisions!D9=1,"KillInfra ","")&IF(Decisions!D10=1,"FastAR ","")&IF(Decisions!D11=1,"Fundraise",""))," ","+")) -> CutMktg+FrzHire | E56: ='Cash Flow Model'!I25 -> 48258 | F56: 7 | G56: 2025-07-01 | H56: —
A57: 2025-08 | B57: Net | C57: Net Cash Flow | D57: =IF(SUMPRODUCT((Decisions!D4:D11=1)*1)=0,"Baseline",SUBSTITUTE(TRIM(IF(Decisions!D4=1,"CutMktg ","")&IF(Decisions!D5=1,"CutHead ","")&IF(Decisions!D6=1,"FrzHire ","")&IF(Decisions!D7=1,"PriceUp ","")&IF(Decisions!D8=1,"RetChurn ","")&IF(Decisions!D9=1,"KillInfra ","")&IF(Decisions!D10=1,"FastAR ","")&IF(Decisions!D11=1,"Fundraise",""))," ","+")) -> CutMktg+FrzHire | E57: ='Cash Flow Model'!J25 -> 43539 | F57: 8 | G57: 2025-08-01 | H57: —
A58: 2025-09 | B58: Net | C58: Net Cash Flow | D58: =IF(SUMPRODUCT((Decisions!D4:D11=1)*1)=0,"Baseline",SUBSTITUTE(TRIM(IF(Decisions!D4=1,"CutMktg ","")&IF(Decisions!D5=1,"CutHead ","")&IF(Decisions!D6=1,"FrzHire ","")&IF(Decisions!D7=1,"PriceUp ","")&IF(Decisions!D8=1,"RetChurn ","")&IF(Decisions!D9=1,"KillInfra ","")&IF(Decisions!D10=1,"FastAR ","")&IF(Decisions!D11=1,"Fundraise",""))," ","+")) -> CutMktg+FrzHire | E58: ='Cash Flow Model'!K25 -> 24239 | F58: 9 | G58: 2025-09-01 | H58: —
A59: 2025-10 | B59: Net | C59: Net Cash Flow | D59: =IF(SUMPRODUCT((Decisions!D4:D11=1)*1)=0,"Baseline",SUBSTITUTE(TRIM(IF(Decisions!D4=1,"CutMktg ","")&IF(Decisions!D5=1,"CutHead ","")&IF(Decisions!D6=1,"FrzHire ","")&IF(Decisions!D7=1,"PriceUp ","")&IF(Decisions!D8=1,"RetChurn ","")&IF(Decisions!D9=1,"KillInfra ","")&IF(Decisions!D10=1,"FastAR ","")&IF(Decisions!D11=1,"Fundraise",""))," ","+")) -> CutMktg+FrzHire | E59: ='Cash Flow Model'!L25 -> 21546 | F59: 10 | G59: 2025-10-01 | H59: —
A60: 2025-11 | B60: Net | C60: Net Cash Flow | D60: =IF(SUMPRODUCT((Decisions!D4:D11=1)*1)=0,"Baseline",SUBSTITUTE(TRIM(IF(Decisions!D4=1,"CutMktg ","")&IF(Decisions!D5=1,"CutHead ","")&IF(Decisions!D6=1,"FrzHire ","")&IF(Decisions!D7=1,"PriceUp ","")&IF(Decisions!D8=1,"RetChurn ","")&IF(Decisions!D9=1,"KillInfra ","")&IF(Decisions!D10=1,"FastAR ","")&IF(Decisions!D11=1,"Fundraise",""))," ","+")) -> CutMktg+FrzHire | E60: ='Cash Flow Model'!M25 -> 17661 | F60: 11 | G60: 2025-11-01 | H60: —
A61: 2025-12 | B61: Net | C61: Net Cash Flow | D61: =IF(SUMPRODUCT((Decisions!D4:D11=1)*1)=0,"Baseline",SUBSTITUTE(TRIM(IF(Decisions!D4=1,"CutMktg ","")&IF(Decisions!D5=1,"CutHead ","")&IF(Decisions!D6=1,"FrzHire ","")&IF(Decisions!D7=1,"PriceUp ","")&IF(Decisions!D8=1,"RetChurn ","")&IF(Decisions!D9=1,"KillInfra ","")&IF(Decisions!D10=1,"FastAR ","")&IF(Decisions!D11=1,"Fundraise",""))," ","+")) -> CutMktg+FrzHire | E61: ='Cash Flow Model'!N25 -> 16606 | F61: 12 | G61: 2025-12-01 | H61: —
A62: 2026-01 | B62: Net | C62: Net Cash Flow | D62: =IF(SUMPRODUCT((Decisions!D4:D11=1)*1)=0,"Baseline",SUBSTITUTE(TRIM(IF(Decisions!D4=1,"CutMktg ","")&IF(Decisions!D5=1,"CutHead ","")&IF(Decisions!D6=1,"FrzHire ","")&IF(Decisions!D7=1,"PriceUp ","")&IF(Decisions!D8=1,"RetChurn ","")&IF(Decisions!D9=1,"KillInfra ","")&IF(Decisions!D10=1,"FastAR ","")&IF(Decisions!D11=1,"Fundraise",""))," ","+")) -> CutMktg+FrzHire | E62: ='Cash Flow Model'!O25 -> 16323 | F62: 13 | G62: 2026-01-01 | H62: —
A63: 2026-02 | B63: Net | C63: Net Cash Flow | D63: =IF(SUMPRODUCT((Decisions!D4:D11=1)*1)=0,"Baseline",SUBSTITUTE(TRIM(IF(Decisions!D4=1,"CutMktg ","")&IF(Decisions!D5=1,"CutHead ","")&IF(Decisions!D6=1,"FrzHire ","")&IF(Decisions!D7=1,"PriceUp ","")&IF(Decisions!D8=1,"RetChurn ","")&IF(Decisions!D9=1,"KillInfra ","")&IF(Decisions!D10=1,"FastAR ","")&IF(Decisions!D11=1,"Fundraise",""))," ","+")) -> CutMktg+FrzHire | E63: ='Cash Flow Model'!P25 -> 16689 | F63: 14 | G63: 2026-02-01 | H63: —
A64: 2026-03 | B64: Net | C64: Net Cash Flow | D64: =IF(SUMPRODUCT((Decisions!D4:D11=1)*1)=0,"Baseline",SUBSTITUTE(TRIM(IF(Decisions!D4=1,"CutMktg ","")&IF(Decisions!D5=1,"CutHead ","")&IF(Decisions!D6=1,"FrzHire ","")&IF(Decisions!D7=1,"PriceUp ","")&IF(Decisions!D8=1,"RetChurn ","")&IF(Decisions!D9=1,"KillInfra ","")&IF(Decisions!D10=1,"FastAR ","")&IF(Decisions!D11=1,"Fundraise",""))," ","+")) -> CutMktg+FrzHire | E64: ='Cash Flow Model'!Q25 -> 17736 | F64: 15 | G64: 2026-03-01 | H64: —
A65: 2026-04 | B65: Net | C65: Net Cash Flow | D65: =IF(SUMPRODUCT((Decisions!D4:D11=1)*1)=0,"Baseline",SUBSTITUTE(TRIM(IF(Decisions!D4=1,"CutMktg ","")&IF(Decisions!D5=1,"CutHead ","")&IF(Decisions!D6=1,"FrzHire ","")&IF(Decisions!D7=1,"PriceUp ","")&IF(Decisions!D8=1,"RetChurn ","")&IF(Decisions!D9=1,"KillInfra ","")&IF(Decisions!D10=1,"FastAR ","")&IF(Decisions!D11=1,"Fundraise",""))," ","+")) -> CutMktg+FrzHire | E65: ='Cash Flow Model'!R25 -> 19383 | F65: 16 | G65: 2026-04-01 | H65: —
A66: 2026-05 | B66: Net | C66: Net Cash Flow | D66: =IF(SUMPRODUCT((Decisions!D4:D11=1)*1)=0,"Baseline",SUBSTITUTE(TRIM(IF(Decisions!D4=1,"CutMktg ","")&IF(Decisions!D5=1,"CutHead ","")&IF(Decisions!D6=1,"FrzHire ","")&IF(Decisions!D7=1,"PriceUp ","")&IF(Decisions!D8=1,"RetChurn ","")&IF(Decisions!D9=1,"KillInfra ","")&IF(Decisions!D10=1,"FastAR ","")&IF(Decisions!D11=1,"Fundraise",""))," ","+")) -> CutMktg+FrzHire | E66: ='Cash Flow Model'!S25 -> 21528 | F66: 17 | G66: 2026-05-01 | H66: —
A67: 2026-06 | B67: Net | C67: Net Cash Flow | D67: =IF(SUMPRODUCT((Decisions!D4:D11=1)*1)=0,"Baseline",SUBSTITUTE(TRIM(IF(Decisions!D4=1,"CutMktg ","")&IF(Decisions!D5=1,"CutHead ","")&IF(Decisions!D6=1,"FrzHire ","")&IF(Decisions!D7=1,"PriceUp ","")&IF(Decisions!D8=1,"RetChurn ","")&IF(Decisions!D9=1,"KillInfra ","")&IF(Decisions!D10=1,"FastAR ","")&IF(Decisions!D11=1,"Fundraise",""))," ","+")) -> CutMktg+FrzHire | E67: ='Cash Flow Model'!T25 -> 24223 | F67: 18 | G67: 2026-06-01 | H67: —
A68: 2026-07 | B68: Net | C68: Net Cash Flow | D68: =IF(SUMPRODUCT((Decisions!D4:D11=1)*1)=0,"Baseline",SUBSTITUTE(TRIM(IF(Decisions!D4=1,"CutMktg ","")&IF(Decisions!D5=1,"CutHead ","")&IF(Decisions!D6=1,"FrzHire ","")&IF(Decisions!D7=1,"PriceUp ","")&IF(Decisions!D8=1,"RetChurn ","")&IF(Decisions!D9=1,"KillInfra ","")&IF(Decisions!D10=1,"FastAR ","")&IF(Decisions!D11=1,"Fundraise",""))," ","+")) -> CutMktg+FrzHire | E68: ='Cash Flow Model'!U25 -> 27370 | F68: 19 | G68: 2026-07-01 | H68: —
A69: 2026-08 | B69: Net | C69: Net Cash Flow | D69: =IF(SUMPRODUCT((Decisions!D4:D11=1)*1)=0,"Baseline",SUBSTITUTE(TRIM(IF(Decisions!D4=1,"CutMktg ","")&IF(Decisions!D5=1,"CutHead ","")&IF(Decisions!D6=1,"FrzHire ","")&IF(Decisions!D7=1,"PriceUp ","")&IF(Decisions!D8=1,"RetChurn ","")&IF(Decisions!D9=1,"KillInfra ","")&IF(Decisions!D10=1,"FastAR ","")&IF(Decisions!D11=1,"Fundraise",""))," ","+")) -> CutMktg+FrzHire | E69: ='Cash Flow Model'!V25 -> 31028 | F69: 20 | G69: 2026-08-01 | H69: —
A70: 2026-09 | B70: Net | C70: Net Cash Flow | D70: =IF(SUMPRODUCT((Decisions!D4:D11=1)*1)=0,"Baseline",SUBSTITUTE(TRIM(IF(Decisions!D4=1,"CutMktg ","")&IF(Decisions!D5=1,"CutHead ","")&IF(Decisions!D6=1,"FrzHire ","")&IF(Decisions!D7=1,"PriceUp ","")&IF(Decisions!D8=1,"RetChurn ","")&IF(Decisions!D9=1,"KillInfra ","")&IF(Decisions!D10=1,"FastAR ","")&IF(Decisions!D11=1,"Fundraise",""))," ","+")) -> CutMktg+FrzHire | E70: ='Cash Flow Model'!W25 -> 35105 | F70: 21 | G70: 2026-09-01 | H70: —
A71: 2026-10 | B71: Net | C71: Net Cash Flow | D71: =IF(SUMPRODUCT((Decisions!D4:D11=1)*1)=0,"Baseline",SUBSTITUTE(TRIM(IF(Decisions!D4=1,"CutMktg ","")&IF(Decisions!D5=1,"CutHead ","")&IF(Decisions!D6=1,"FrzHire ","")&IF(Decisions!D7=1,"PriceUp ","")&IF(Decisions!D8=1,"RetChurn ","")&IF(Decisions!D9=1,"KillInfra ","")&IF(Decisions!D10=1,"FastAR ","")&IF(Decisions!D11=1,"Fundraise",""))," ","+")) -> CutMktg+FrzHire | E71: ='Cash Flow Model'!X25 -> 39631 | F71: 22 | G71: 2026-10-01 | H71: —
A72: 2026-11 | B72: Net | C72: Net Cash Flow | D72: =IF(SUMPRODUCT((Decisions!D4:D11=1)*1)=0,"Baseline",SUBSTITUTE(TRIM(IF(Decisions!D4=1,"CutMktg ","")&IF(Decisions!D5=1,"CutHead ","")&IF(Decisions!D6=1,"FrzHire ","")&IF(Decisions!D7=1,"PriceUp ","")&IF(Decisions!D8=1,"RetChurn ","")&IF(Decisions!D9=1,"KillInfra ","")&IF(Decisions!D10=1,"FastAR ","")&IF(Decisions!D11=1,"Fundraise",""))," ","+")) -> CutMktg+FrzHire | E72: ='Cash Flow Model'!Y25 -> 44664 | F72: 23 | G72: 2026-11-01 | H72: —
A73: 2026-12 | B73: Net | C73: Net Cash Flow | D73: =IF(SUMPRODUCT((Decisions!D4:D11=1)*1)=0,"Baseline",SUBSTITUTE(TRIM(IF(Decisions!D4=1,"CutMktg ","")&IF(Decisions!D5=1,"CutHead ","")&IF(Decisions!D6=1,"FrzHire ","")&IF(Decisions!D7=1,"PriceUp ","")&IF(Decisions!D8=1,"RetChurn ","")&IF(Decisions!D9=1,"KillInfra ","")&IF(Decisions!D10=1,"FastAR ","")&IF(Decisions!D11=1,"Fundraise",""))," ","+")) -> CutMktg+FrzHire | E73: ='Cash Flow Model'!Z25 -> 50112 | F73: 24 | G73: 2026-12-01 | H73: —
A74: 2025-01 | B74: Balance | C74: Closing Balance | D74: =IF(SUMPRODUCT((Decisions!D4:D11=1)*1)=0,"Baseline",SUBSTITUTE(TRIM(IF(Decisions!D4=1,"CutMktg ","")&IF(Decisions!D5=1,"CutHead ","")&IF(Decisions!D6=1,"FrzHire ","")&IF(Decisions!D7=1,"PriceUp ","")&IF(Decisions!D8=1,"RetChurn ","")&IF(Decisions!D9=1,"KillInfra ","")&IF(Decisions!D10=1,"FastAR ","")&IF(Decisions!D11=1,"Fundraise",""))," ","+")) -> CutMktg+FrzHire | E74: ='Cash Flow Model'!C26 -> 391920 | F74: 1 | G74: 2025-01-01 | H74: —
A75: 2025-02 | B75: Balance | C75: Closing Balance | D75: =IF(SUMPRODUCT((Decisions!D4:D11=1)*1)=0,"Baseline",SUBSTITUTE(TRIM(IF(Decisions!D4=1,"CutMktg ","")&IF(Decisions!D5=1,"CutHead ","")&IF(Decisions!D6=1,"FrzHire ","")&IF(Decisions!D7=1,"PriceUp ","")&IF(Decisions!D8=1,"RetChurn ","")&IF(Decisions!D9=1,"KillInfra ","")&IF(Decisions!D10=1,"FastAR ","")&IF(Decisions!D11=1,"Fundraise",""))," ","+")) -> CutMktg+FrzHire | E75: ='Cash Flow Model'!D26 -> 401904 | F75: 2 | G75: 2025-02-01 | H75: —
A76: 2025-03 | B76: Balance | C76: Closing Balance | D76: =IF(SUMPRODUCT((Decisions!D4:D11=1)*1)=0,"Baseline",SUBSTITUTE(TRIM(IF(Decisions!D4=1,"CutMktg ","")&IF(Decisions!D5=1,"CutHead ","")&IF(Decisions!D6=1,"FrzHire ","")&IF(Decisions!D7=1,"PriceUp ","")&IF(Decisions!D8=1,"RetChurn ","")&IF(Decisions!D9=1,"KillInfra ","")&IF(Decisions!D10=1,"FastAR ","")&IF(Decisions!D11=1,"Fundraise",""))," ","+")) -> CutMktg+FrzHire | E76: ='Cash Flow Model'!E26 -> 418399 | F76: 3 | G76: 2025-03-01 | H76: —
A77: 2025-04 | B77: Balance | C77: Closing Balance | D77: =IF(SUMPRODUCT((Decisions!D4:D11=1)*1)=0,"Baseline",SUBSTITUTE(TRIM(IF(Decisions!D4=1,"CutMktg ","")&IF(Decisions!D5=1,"CutHead ","")&IF(Decisions!D6=1,"FrzHire ","")&IF(Decisions!D7=1,"PriceUp ","")&IF(Decisions!D8=1,"RetChurn ","")&IF(Decisions!D9=1,"KillInfra ","")&IF(Decisions!D10=1,"FastAR ","")&IF(Decisions!D11=1,"Fundraise",""))," ","+")) -> CutMktg+FrzHire | E77: ='Cash Flow Model'!F26 -> 441415 | F77: 4 | G77: 2025-04-01 | H77: —
A78: 2025-05 | B78: Balance | C78: Closing Balance | D78: =IF(SUMPRODUCT((Decisions!D4:D11=1)*1)=0,"Baseline",SUBSTITUTE(TRIM(IF(Decisions!D4=1,"CutMktg ","")&IF(Decisions!D5=1,"CutHead ","")&IF(Decisions!D6=1,"FrzHire ","")&IF(Decisions!D7=1,"PriceUp ","")&IF(Decisions!D8=1,"RetChurn ","")&IF(Decisions!D9=1,"KillInfra ","")&IF(Decisions!D10=1,"FastAR ","")&IF(Decisions!D11=1,"Fundraise",""))," ","+")) -> CutMktg+FrzHire | E78: ='Cash Flow Model'!G26 -> 471069 | F78: 5 | G78: 2025-05-01 | H78: —
A79: 2025-06 | B79: Balance | C79: Closing Balance | D79: =IF(SUMPRODUCT((Decisions!D4:D11=1)*1)=0,"Baseline",SUBSTITUTE(TRIM(IF(Decisions!D4=1,"CutMktg ","")&IF(Decisions!D5=1,"CutHead ","")&IF(Decisions!D6=1,"FrzHire ","")&IF(Decisions!D7=1,"PriceUp ","")&IF(Decisions!D8=1,"RetChurn ","")&IF(Decisions!D9=1,"KillInfra ","")&IF(Decisions!D10=1,"FastAR ","")&IF(Decisions!D11=1,"Fundraise",""))," ","+")) -> CutMktg+FrzHire | E79: ='Cash Flow Model'!H26 -> 507695 | F79: 6 | G79: 2025-06-01 | H79: —
A80: 2025-07 | B80: Balance | C80: Closing Balance | D80: =IF(SUMPRODUCT((Decisions!D4:D11=1)*1)=0,"Baseline",SUBSTITUTE(TRIM(IF(Decisions!D4=1,"CutMktg ","")&IF(Decisions!D5=1,"CutHead ","")&IF(Decisions!D6=1,"FrzHire ","")&IF(Decisions!D7=1,"PriceUp ","")&IF(Decisions!D8=1,"RetChurn ","")&IF(Decisions!D9=1,"KillInfra ","")&IF(Decisions!D10=1,"FastAR ","")&IF(Decisions!D11=1,"Fundraise",""))," ","+")) -> CutMktg+FrzHire | E80: ='Cash Flow Model'!I26 -> 555953 | F80: 7 | G80: 2025-07-01 | H80: —
A81: 2025-08 | B81: Balance | C81: Closing Balance | D81: =IF(SUMPRODUCT((Decisions!D4:D11=1)*1)=0,"Baseline",SUBSTITUTE(TRIM(IF(Decisions!D4=1,"CutMktg ","")&IF(Decisions!D5=1,"CutHead ","")&IF(Decisions!D6=1,"FrzHire ","")&IF(Decisions!D7=1,"PriceUp ","")&IF(Decisions!D8=1,"RetChurn ","")&IF(Decisions!D9=1,"KillInfra ","")&IF(Decisions!D10=1,"FastAR ","")&IF(Decisions!D11=1,"Fundraise",""))," ","+")) -> CutMktg+FrzHire | E81: ='Cash Flow Model'!J26 -> 599492 | F81: 8 | G81: 2025-08-01 | H81: —
A82: 2025-09 | B82: Balance | C82: Closing Balance | D82: =IF(SUMPRODUCT((Decisions!D4:D11=1)*1)=0,"Baseline",SUBSTITUTE(TRIM(IF(Decisions!D4=1,"CutMktg ","")&IF(Decisions!D5=1,"CutHead ","")&IF(Decisions!D6=1,"FrzHire ","")&IF(Decisions!D7=1,"PriceUp ","")&IF(Decisions!D8=1,"RetChurn ","")&IF(Decisions!D9=1,"KillInfra ","")&IF(Decisions!D10=1,"FastAR ","")&IF(Decisions!D11=1,"Fundraise",""))," ","+")) -> CutMktg+FrzHire | E82: ='Cash Flow Model'!K26 -> 623731 | F82: 9 | G82: 2025-09-01 | H82: —
A83: 2025-10 | B83: Balance | C83: Closing Balance | D83: =IF(SUMPRODUCT((Decisions!D4:D11=1)*1)=0,"Baseline",SUBSTITUTE(TRIM(IF(Decisions!D4=1,"CutMktg ","")&IF(Decisions!D5=1,"CutHead ","")&IF(Decisions!D6=1,"FrzHire ","")&IF(Decisions!D7=1,"PriceUp ","")&IF(Decisions!D8=1,"RetChurn ","")&IF(Decisions!D9=1,"KillInfra ","")&IF(Decisions!D10=1,"FastAR ","")&IF(Decisions!D11=1,"Fundraise",""))," ","+")) -> CutMktg+FrzHire | E83: ='Cash Flow Model'!L26 -> 645277 | F83: 10 | G83: 2025-10-01 | H83: —
A84: 2025-11 | B84: Balance | C84: Closing Balance | D84: =IF(SUMPRODUCT((Decisions!D4:D11=1)*1)=0,"Baseline",SUBSTITUTE(TRIM(IF(Decisions!D4=1,"CutMktg ","")&IF(Decisions!D5=1,"CutHead ","")&IF(Decisions!D6=1,"FrzHire ","")&IF(Decisions!D7=1,"PriceUp ","")&IF(Decisions!D8=1,"RetChurn ","")&IF(Decisions!D9=1,"KillInfra ","")&IF(Decisions!D10=1,"FastAR ","")&IF(Decisions!D11=1,"Fundraise",""))," ","+")) -> CutMktg+FrzHire | E84: ='Cash Flow Model'!M26 -> 662938 | F84: 11 | G84: 2025-11-01 | H84: —
A85: 2025-12 | B85: Balance | C85: Closing Balance | D85: =IF(SUMPRODUCT((Decisions!D4:D11=1)*1)=0,"Baseline",SUBSTITUTE(TRIM(IF(Decisions!D4=1,"CutMktg ","")&IF(Decisions!D5=1,"CutHead ","")&IF(Decisions!D6=1,"FrzHire ","")&IF(Decisions!D7=1,"PriceUp ","")&IF(Decisions!D8=1,"RetChurn ","")&IF(Decisions!D9=1,"KillInfra ","")&IF(Decisions!D10=1,"FastAR ","")&IF(Decisions!D11=1,"Fundraise",""))," ","+")) -> CutMktg+FrzHire | E85: ='Cash Flow Model'!N26 -> 679544 | F85: 12 | G85: 2025-12-01 | H85: —
A86: 2026-01 | B86: Balance | C86: Closing Balance | D86: =IF(SUMPRODUCT((Decisions!D4:D11=1)*1)=0,"Baseline",SUBSTITUTE(TRIM(IF(Decisions!D4=1,"CutMktg ","")&IF(Decisions!D5=1,"CutHead ","")&IF(Decisions!D6=1,"FrzHire ","")&IF(Decisions!D7=1,"PriceUp ","")&IF(Decisions!D8=1,"RetChurn ","")&IF(Decisions!D9=1,"KillInfra ","")&IF(Decisions!D10=1,"FastAR ","")&IF(Decisions!D11=1,"Fundraise",""))," ","+")) -> CutMktg+FrzHire | E86: ='Cash Flow Model'!O26 -> 695867 | F86: 13 | G86: 2026-01-01 | H86: —
A87: 2026-02 | B87: Balance | C87: Closing Balance | D87: =IF(SUMPRODUCT((Decisions!D4:D11=1)*1)=0,"Baseline",SUBSTITUTE(TRIM(IF(Decisions!D4=1,"CutMktg ","")&IF(Decisions!D5=1,"CutHead ","")&IF(Decisions!D6=1,"FrzHire ","")&IF(Decisions!D7=1,"PriceUp ","")&IF(Decisions!D8=1,"RetChurn ","")&IF(Decisions!D9=1,"KillInfra ","")&IF(Decisions!D10=1,"FastAR ","")&IF(Decisions!D11=1,"Fundraise",""))," ","+")) -> CutMktg+FrzHire | E87: ='Cash Flow Model'!P26 -> 712556 | F87: 14 | G87: 2026-02-01 | H87: —
A88: 2026-03 | B88: Balance | C88: Closing Balance | D88: =IF(SUMPRODUCT((Decisions!D4:D11=1)*1)=0,"Baseline",SUBSTITUTE(TRIM(IF(Decisions!D4=1,"CutMktg ","")&IF(Decisions!D5=1,"CutHead ","")&IF(Decisions!D6=1,"FrzHire ","")&IF(Decisions!D7=1,"PriceUp ","")&IF(Decisions!D8=1,"RetChurn ","")&IF(Decisions!D9=1,"KillInfra ","")&IF(Decisions!D10=1,"FastAR ","")&IF(Decisions!D11=1,"Fundraise",""))," ","+")) -> CutMktg+FrzHire | E88: ='Cash Flow Model'!Q26 -> 730292 | F88: 15 | G88: 2026-03-01 | H88: —
A89: 2026-04 | B89: Balance | C89: Closing Balance | D89: =IF(SUMPRODUCT((Decisions!D4:D11=1)*1)=0,"Baseline",SUBSTITUTE(TRIM(IF(Decisions!D4=1,"CutMktg ","")&IF(Decisions!D5=1,"CutHead ","")&IF(Decisions!D6=1,"FrzHire ","")&IF(Decisions!D7=1,"PriceUp ","")&IF(Decisions!D8=1,"RetChurn ","")&IF(Decisions!D9=1,"KillInfra ","")&IF(Decisions!D10=1,"FastAR ","")&IF(Decisions!D11=1,"Fundraise",""))," ","+")) -> CutMktg+FrzHire | E89: ='Cash Flow Model'!R26 -> 749675 | F89: 16 | G89: 2026-04-01 | H89: —
A90: 2026-05 | B90: Balance | C90: Closing Balance | D90: =IF(SUMPRODUCT((Decisions!D4:D11=1)*1)=0,"Baseline",SUBSTITUTE(TRIM(IF(Decisions!D4=1,"CutMktg ","")&IF(Decisions!D5=1,"CutHead ","")&IF(Decisions!D6=1,"FrzHire ","")&IF(Decisions!D7=1,"PriceUp ","")&IF(Decisions!D8=1,"RetChurn ","")&IF(Decisions!D9=1,"KillInfra ","")&IF(Decisions!D10=1,"FastAR ","")&IF(Decisions!D11=1,"Fundraise",""))," ","+")) -> CutMktg+FrzHire | E90: ='Cash Flow Model'!S26 -> 771203 | F90: 17 | G90: 2026-05-01 | H90: —
A91: 2026-06 | B91: Balance | C91: Closing Balance | D91: =IF(SUMPRODUCT((Decisions!D4:D11=1)*1)=0,"Baseline",SUBSTITUTE(TRIM(IF(Decisions!D4=1,"CutMktg ","")&IF(Decisions!D5=1,"CutHead ","")&IF(Decisions!D6=1,"FrzHire ","")&IF(Decisions!D7=1,"PriceUp ","")&IF(Decisions!D8=1,"RetChurn ","")&IF(Decisions!D9=1,"KillInfra ","")&IF(Decisions!D10=1,"FastAR ","")&IF(Decisions!D11=1,"Fundraise",""))," ","+")) -> CutMktg+FrzHire | E91: ='Cash Flow Model'!T26 -> 795426 | F91: 18 | G91: 2026-06-01 | H91: —
A92: 2026-07 | B92: Balance | C92: Closing Balance | D92: =IF(SUMPRODUCT((Decisions!D4:D11=1)*1)=0,"Baseline",SUBSTITUTE(TRIM(IF(Decisions!D4=1,"CutMktg ","")&IF(Decisions!D5=1,"CutHead ","")&IF(Decisions!D6=1,"FrzHire ","")&IF(Decisions!D7=1,"PriceUp ","")&IF(Decisions!D8=1,"RetChurn ","")&IF(Decisions!D9=1,"KillInfra ","")&IF(Decisions!D10=1,"FastAR ","")&IF(Decisions!D11=1,"Fundraise",""))," ","+")) -> CutMktg+FrzHire | E92: ='Cash Flow Model'!U26 -> 822796 | F92: 19 | G92: 2026-07-01 | H92: —
A93: 2026-08 | B93: Balance | C93: Closing Balance | D93: =IF(SUMPRODUCT((Decisions!D4:D11=1)*1)=0,"Baseline",SUBSTITUTE(TRIM(IF(Decisions!D4=1,"CutMktg ","")&IF(Decisions!D5=1,"CutHead ","")&IF(Decisions!D6=1,"FrzHire ","")&IF(Decisions!D7=1,"PriceUp ","")&IF(Decisions!D8=1,"RetChurn ","")&IF(Decisions!D9=1,"KillInfra ","")&IF(Decisions!D10=1,"FastAR ","")&IF(Decisions!D11=1,"Fundraise",""))," ","+")) -> CutMktg+FrzHire | E93: ='Cash Flow Model'!V26 -> 853824 | F93: 20 | G93: 2026-08-01 | H93: —
A94: 2026-09 | B94: Balance | C94: Closing Balance | D94: =IF(SUMPRODUCT((Decisions!D4:D11=1)*1)=0,"Baseline",SUBSTITUTE(TRIM(IF(Decisions!D4=1,"CutMktg ","")&IF(Decisions!D5=1,"CutHead ","")&IF(Decisions!D6=1,"FrzHire ","")&IF(Decisions!D7=1,"PriceUp ","")&IF(Decisions!D8=1,"RetChurn ","")&IF(Decisions!D9=1,"KillInfra ","")&IF(Decisions!D10=1,"FastAR ","")&IF(Decisions!D11=1,"Fundraise",""))," ","+")) -> CutMktg+FrzHire | E94: ='Cash Flow Model'!W26 -> 888929 | F94: 21 | G94: 2026-09-01 | H94: —
A95: 2026-10 | B95: Balance | C95: Closing Balance | D95: =IF(SUMPRODUCT((Decisions!D4:D11=1)*1)=0,"Baseline",SUBSTITUTE(TRIM(IF(Decisions!D4=1,"CutMktg ","")&IF(Decisions!D5=1,"CutHead ","")&IF(Decisions!D6=1,"FrzHire ","")&IF(Decisions!D7=1,"PriceUp ","")&IF(Decisions!D8=1,"RetChurn ","")&IF(Decisions!D9=1,"KillInfra ","")&IF(Decisions!D10=1,"FastAR ","")&IF(Decisions!D11=1,"Fundraise",""))," ","+")) -> CutMktg+FrzHire | E95: ='Cash Flow Model'!X26 -> 928560 | F95: 22 | G95: 2026-10-01 | H95: —
A96: 2026-11 | B96: Balance | C96: Closing Balance | D96: =IF(SUMPRODUCT((Decisions!D4:D11=1)*1)=0,"Baseline",SUBSTITUTE(TRIM(IF(Decisions!D4=1,"CutMktg ","")&IF(Decisions!D5=1,"CutHead ","")&IF(Decisions!D6=1,"FrzHire ","")&IF(Decisions!D7=1,"PriceUp ","")&IF(Decisions!D8=1,"RetChurn ","")&IF(Decisions!D9=1,"KillInfra ","")&IF(Decisions!D10=1,"FastAR ","")&IF(Decisions!D11=1,"Fundraise",""))," ","+")) -> CutMktg+FrzHire | E96: ='Cash Flow Model'!Y26 -> 973224 | F96: 23 | G96: 2026-11-01 | H96: —
A97: 2026-12 | B97: Balance | C97: Closing Balance | D97: =IF(SUMPRODUCT((Decisions!D4:D11=1)*1)=0,"Baseline",SUBSTITUTE(TRIM(IF(Decisions!D4=1,"CutMktg ","")&IF(Decisions!D5=1,"CutHead ","")&IF(Decisions!D6=1,"FrzHire ","")&IF(Decisions!D7=1,"PriceUp ","")&IF(Decisions!D8=1,"RetChurn ","")&IF(Decisions!D9=1,"KillInfra ","")&IF(Decisions!D10=1,"FastAR ","")&IF(Decisions!D11=1,"Fundraise",""))," ","+")) -> CutMktg+FrzHire | E97: ='Cash Flow Model'!Z26 -> 1023336 | F97: 24 | G97: 2026-12-01 | H97: —
A98: 2025-01 | B98: KPI | C98: Burn Rate | D98: =IF(SUMPRODUCT((Decisions!D4:D11=1)*1)=0,"Baseline",SUBSTITUTE(TRIM(IF(Decisions!D4=1,"CutMktg ","")&IF(Decisions!D5=1,"CutHead ","")&IF(Decisions!D6=1,"FrzHire ","")&IF(Decisions!D7=1,"PriceUp ","")&IF(Decisions!D8=1,"RetChurn ","")&IF(Decisions!D9=1,"KillInfra ","")&IF(Decisions!D10=1,"FastAR ","")&IF(Decisions!D11=1,"Fundraise",""))," ","+")) -> CutMktg+FrzHire | E98: ='Cash Flow Model'!C28 -> 108080 | F98: 1 | G98: 2025-01-01 | H98: —
A99: 2025-02 | B99: KPI | C99: Burn Rate | D99: =IF(SUMPRODUCT((Decisions!D4:D11=1)*1)=0,"Baseline",SUBSTITUTE(TRIM(IF(Decisions!D4=1,"CutMktg ","")&IF(Decisions!D5=1,"CutHead ","")&IF(Decisions!D6=1,"FrzHire ","")&IF(Decisions!D7=1,"PriceUp ","")&IF(Decisions!D8=1,"RetChurn ","")&IF(Decisions!D9=1,"KillInfra ","")&IF(Decisions!D10=1,"FastAR ","")&IF(Decisions!D11=1,"Fundraise",""))," ","+")) -> CutMktg+FrzHire | E99: ='Cash Flow Model'!D28 -> 0 | F99: 2 | G99: 2025-02-01 | H99: —
A100: 2025-03 | B100: KPI | C100: Burn Rate | D100: =IF(SUMPRODUCT((Decisions!D4:D11=1)*1)=0,"Baseline",SUBSTITUTE(TRIM(IF(Decisions!D4=1,"CutMktg ","")&IF(Decisions!D5=1,"CutHead ","")&IF(Decisions!D6=1,"FrzHire ","")&IF(Decisions!D7=1,"PriceUp ","")&IF(Decisions!D8=1,"RetChurn ","")&IF(Decisions!D9=1,"KillInfra ","")&IF(Decisions!D10=1,"FastAR ","")&IF(Decisions!D11=1,"Fundraise",""))," ","+")) -> CutMktg+FrzHire | E100: ='Cash Flow Model'!E28 -> 0 | F100: 3 | G100: 2025-03-01 | H100: —
...
